Workbook

Sheet Start Here
A1: Farm Intelligence Source Registry
A3: What this is | B3: A working list of trusted sources for supply, demand, price, trade and driver signals that affect farms, tagged by commodity group, driver, horizon, and trust tier.
A4: Tabs | B4: Source Registry (the list) | Driver Coverage (live counts, including independence) | Root Check (test whether sources are really independent) | MVP Sources (the first 15 sources, by build wave) | Trigger Map (trigger families and the sources that detect them) | Lens to Sources (how the strategic lens selects sources) | Policy Map (policy levers and coverage by commodity) | Policy Alert Rules (when a policy item becomes an alert) | Coverage Checklist (what the registry should cover, and where gaps remain) | Commodity Nodes (upstream, co-products, downstream)
A5: What to edit | B5: Yellow cells in the Pipeline status column (and the source ID cells on Root Check). Update status as sources move from scoped to connected to live. Add new rows at the bottom of the registry; the coverage tab recalculates.
A6: Authority tier 1 | B6: Official statistic: government or intergovernmental data. Authoritative, but lags.
A7: Authority tier 2 | B7: Market price, exchange, or trade-body data and structured analyst baselines. Timely, with method caveats.
A8: Authority tier 3 | B8: Analyst or advocacy interpretation. Useful for context; label as opinion.
A9: Retrieval tier | B9: 0 = synthesized house sources (driver briefs, Future State material, diversification library); 1 = curated secondary sources (outlooks, analysis, advocacy, news); 2 = primary data. Agents look in this order and use tier 2 only to fetch a current value, fill a gap, or verify. This is separate from authority tier.
A10: System role | B10: Detection feed = watched to detect triggers. Context = used to explain and frame. Context (synthesized) = retrieval tier 0. Fetch and verify = pulled on demand. Lens prefill = proposes strategic lens fields for the farmer to confirm.
A11: Trigger family | B11: The kind of dynamic change a source helps detect or explain. Policy and regulation is its own family. The Trigger Map tab counts sources by family.
A12: Lens selector and MFP dimension | B12: Which part of the farm's strategic lens decides whether a source is on that farm's watch list, and which MFP dimension the source helps. The Lens to Sources tab explains the logic.
A13: Cache life | B13: How long a fetched value may be reused before it is fetched again.
A14: MVP wave | B14: The 15 sources recommended for the first build, in three waves (yellow, editable). The MVP Sources tab lists them with access watch-outs.
... A22: Caveats | B22: URLs are entry-point pages listed from general knowledge and were not link-checked in this build. Confirm each URL, release schedule, and API terms before automating. Source types, cadences, and access terms change.
A24: Registry rows: | B24: =COUNTA('Source Registry'!$A$2:$A$300) -> 188

Sheet Source Registry
A1: ID | B1: Source | C1: Publisher | D1: Commodity group | E1: Layer | F1: Primary driver | G1: Horizon | H1: Source type | I1: Authority tier | J1: Update cadence | K1: Access | L1: URL | M1: What it answers | N1: Notes | O1: Origin | P1: Depends on | Q1: Root ID | R1: Independent signal | S1: What it adds | T1: Pipeline status | U1: Trigger family | V1: System role | W1: Retrieval tier | X1: Lens selector | Y1: MFP dimension served | Z1: Cache life | AA1: MVP wave | AB1: MVP watch-out
A2: S001 | B2: WASDE | C2: USDA OCE / WAOB | D2: Cross-commodity | E2: Balance sheet | F2: Core S&D (baseline) | G2: Near-term (1-2 seasons) | H2: Official statistic | I2: 1 | J2: Monthly | K2: Free download | L2: https://www.usda.gov/oce/commodity/wasde | M2: US and world supply, use, ending stocks and price forecasts for grains, oilseeds, livestock, dairy, sugar, cotton | N2: The monthly benchmark; release dates are published a year ahead | O2: Mixed | P2: S003, S025, S026, S027 | Q2: S001 | R2: Partial | S2: Forecast | T2: Not started | U2: Context only | V2: Fetch and verify | W2: 2 | X2: All farms (context) | Y2: Strategic Vision; Market Analysis | Z2: Days to weeks
A3: S002 | B3: PSD Online | C3: USDA FAS | D3: Cross-commodity | E3: Balance sheet | F3: Core S&D (baseline) | G3: Both | H3: Official statistic | I3: 1 | J3: Monthly | K3: Free API / download | L3: https://apps.fas.usda.gov/psdonline/ | M3: Production, supply and distribution by country (about 200 countries) for major commodities | N3: Global view behind WASDE | O3: Mixed | P3: S003, S025, S027 | Q3: S001 | R3: No | S3: Repackaging | T3: Not started | U3: Context only | V3: Fetch and verify | W3: 2 | X3: All farms (context) | Y3: Strategic Vision; Market Analysis | Z3: Days to weeks
A4: S003 | B4: NASS Quick Stats | C4: USDA NASS | D4: Cross-commodity | E4: Balance sheet | F4: Core S&D (baseline) | G4: Both | H4: Official statistic | I4: 1 | J4: Varies by series | K4: Free API | L4: https://quickstats.nass.usda.gov/ | M4: Production, area, inventories, prices received, by state and county | N4: Best structured API for US farm statistics | O4: Original measurement | Q4: S003 | R4: Yes | S4: New data | T4: Not started | U4: Context only | V4: Fetch and verify | W4: 2 | X4: All farms (context) | Y4: Strategic Vision; Market Analysis | Z4: Days to weeks
A5: S004 | B5: NASS Crop Progress and Grain Stocks | C5: USDA NASS | D5: Grains & oilseeds | E5: Balance sheet | F5: Core S&D (baseline) | G5: Near-term (1-2 seasons) | H5: Official statistic | I5: 1 | J5: Weekly (season) / quarterly | K5: Free download | L5: https://www.nass.usda.gov/Publications/ | M5: Planting and condition ratings, on-farm and off-farm grain stocks | N5: Crop condition is an early yield signal | O5: Original measurement | Q5: S004 | R5: Yes | S5: New data | T5: Not started | U5: Context only | V5: Fetch and verify | W5: 2 | X5: All farms (context) | Y5: Strategic Vision; Market Analysis | Z5: Days to weeks
A6: S005 | B6: NASS Cattle, Cattle on Feed, Hogs and Pigs | C6: USDA NASS | D6: Livestock & poultry | E6: Balance sheet | F6: Core S&D (baseline) | G6: Near-term (1-2 seasons) | H6: Official statistic | I6: 1 | J6: Monthly / quarterly / semiannual | K6: Free API / download | L6: https://www.nass.usda.gov/Publications/ | M6: Herd and inventory size, placements, marketings | N6: Herd size drives multi-year supply | O6: Original measurement | Q6: S005 | R6: Yes | S6: New data | T6: Not started | U6: Context only | V6: Fetch and verify | W6: 2 | X6: All farms (context) | Y6: Strategic Vision; Market Analysis | Z6: Days to weeks
A7: S006 | B7: NASS Milk Production and Dairy Products | C7: USDA NASS | D7: Dairy | E7: Balance sheet | F7: Core S&D (baseline) | G7: Near-term (1-2 seasons) | H7: Official statistic | I7: 1 | J7: Monthly | K7: Free API / download | L7: https://www.nass.usda.gov/Publications/ | M7: Milk output, cow numbers, cheese, butter, whey and dry product production | N7: Whey output follows cheese output | O7: Original measurement | Q7: S006 | R7: Yes | S7: New data | T7: Not started | U7: Context only | V7: Fetch and verify | W7: 2 | X7: All farms (context) | Y7: Strategic Vision; Market Analysis | Z7: Days to weeks
A8: S007 | B8: ERS Dairy and Livestock Outlooks | C8: USDA ERS | D8: Dairy | E8: Balance sheet | F8: Core S&D (baseline) | G8: Near-term (1-2 seasons) | H8: Official statistic | I8: 1 | J8: Monthly | K8: Free download | L8: https://www.ers.usda.gov/topics/animal-products/dairy/ | M8: Dairy, livestock, poultry outlook narrative and data tables | N8: Good plain-English context for WASDE numbers | O8: Derived | P8: S001, S006, S017, S005 | Q8: S001 | R8: No | S8: Interpretation | T8: Not started | U8: Context only | V8: Context | W8: 1 | X8: All farms (context) | Y8: Strategic Vision; Market Analysis | Z8: Days to weeks
A9: S008 | B9: ERS Crop Outlooks (feed, wheat, oil crops) | C9: USDA ERS | D9: Grains & oilseeds | E9: Balance sheet | F9: Core S&D (baseline) | G9: Near-term (1-2 seasons) | H9: Official statistic | I9: 1 | J9: Monthly | K9: Free download | L9: https://www.ers.usda.gov/topics/crops/ | M9: Commodity-level outlook, use breakdown, trade | N9: Check the topic page for the current report list | O9: Derived | P9: S001, S003, S026 | Q9: S001 | R9: No | S9: Interpretation | T9: Not started | U9: Context only | V9: Context | W9: 1 | X9: All farms (context) | Y9: Strategic Vision; Market Analysis | Z9: Days to weeks
A10: S009 | B10: ERS Fruit, Tree Nut and Vegetable Outlooks | C10: USDA ERS | D10: Specialty crops | E10: Balance sheet | F10: Core S&D (baseline) | G10: Both | H10: Official statistic | I10: 1 | J10: Periodic | K10: Free download | L10: https://www.ers.usda.gov/topics/crops/ | M10: Production, imports, per-capita use for specialty crops | N10: Fewer formal balance sheets than field crops | O10: Derived | P10: S003, S020, S028 | Q10: S003 | R10: Partial | S10: Interpretation | T10: Not started | U10: Context only | V10: Context | W10: 1 | X10: All farms (context) | Y10: Strategic Vision; Market Analysis | Z10: Days to weeks
A11: S010 | B11: ERS Food Price Outlook | C11: USDA ERS | D11: Cross-commodity | E11: Demand signal | F11: Human Health | G11: Near-term (1-2 seasons) | H11: Official statistic | I11: 1 | J11: Monthly | K11: Free download | L11: https://www.ers.usda.gov/data-products/food-price-outlook/ | M11: Retail food price forecasts by category | N11: Consumer-side price pressure | O11: Mixed | P11: S139 | Q11: S010 | R11: Partial | S11: Forecast | T11: Not started | U11: Context only | V11: Context | W11: 1 | X11: All farms (context) | Y11: Strategic Vision; Market Analysis | Z11: Days to weeks
A12: S011 | B12: ERS Food Availability (per capita) | C12: USDA ERS | D12: Cross-commodity | E12: Demand signal | F12: Human Health | G12: Long-term (3-10 yrs) | H12: Official statistic | I12: 1 | J12: Annual | K12: Free download | L12: https://www.ers.usda.gov/data-products/food-availability-per-capita-data-system/ | M12: Long-run US food consumption by commodity | N12: Shows protein, dairy and sweetener demand shifts | O12: Derived | P12: S003, S028 | Q12: S003 | R12: Partial | S12: Repackaging | T12: Not started | U12: Context only | V12: Fetch and verify | W12: 2 | X12: All farms (context) | Y12: Strategic Vision; Market Analysis | Z12: Days to weeks
A13: S012 | B13: ERS Farm Income Forecast | C13: USDA ERS | D13: Farm economy | E13: Economy | F13: Core S&D (baseline) | G13: Near-term (1-2 seasons) | H13: Official statistic | I13: 1 | J13: Quarterly | K13: Free download | L13: https://www.ers.usda.gov/data-products/farm-income-and-wealth-statistics/ | M13: Net farm income, expenses, debt, government payments | N13: Farm financial health baseline | O13: Derived | P13: S003, S001 | Q13: S003 | R13: Partial | S13: Forecast | T13: Not started | U13: Credit and finance | V13: Context | W13: 1 | X13: Debt and financial health | Y13: Financial Analysis; Risk & Protection | Z13: Days to weeks
A14: S013 | B14: ERS International Macroeconomic Data Set | C14: USDA ERS | D14: Cross-commodity | E14: Demand signal | F14: Global Affluence | G14: Long-term (3-10 yrs) | H14: Official statistic | I14: 1 | J14: Annual | K14: Free download | L14: https://www.ers.usda.gov/data-products/international-macroeconomic-data-set/ | M14: GDP, income and population projections by country | N14: Feeds import-demand projections | O14: Derived | P14: S052, S053 | Q14: S052 | R14: No | S14: Repackaging | T14: Not started | U14: Context only | V14: Fetch and verify | W14: 2 | X14: All farms (context) | Y14: Strategic Vision; Market Analysis | Z14: Days to weeks
A15: S014 | B15: Census of Agriculture | C15: USDA NASS | D15: Ownership | E15: Structure | F15: Ownership | G15: Long-term (3-10 yrs) | H15: Official statistic | I15: 1 | J15: Every 5 years | K15: Free download | L15: https://www.nass.usda.gov/AgCensus/ | M15: Farm numbers, size, operator age, ownership and tenure | N15: Core data for consolidation and succession trends | O15: Original measurement | Q15: S014 | R15: Yes | S15: New data | T15: Not started | U15: Land and ownership | V15: Fetch and verify | W15: 2 | X15: Land tenure and legacy intent | Y15: Succession; Financial Analysis | Z15: Weeks to months
A16: S015 | B16: NASS Land Values | C16: USDA NASS | D16: Ownership | E16: Structure | F16: Ownership | G16: Both | H16: Official statistic | I16: 1 | J16: Annual | K16: Free download | L16: https://www.nass.usda.gov/Publications/ | M16: Cropland and pasture values and cash rents by state | N16: Asset-side view of farm balance sheets | O16: Original measurement | Q16: S015 | R16: Yes | S16: New data | T16: Not started | U16: Land and ownership | V16: Fetch and verify | W16: 2 | X16: Land tenure and legacy intent | Y16: Succession; Financial Analysis | Z16: Weeks to months
A17: S016 | B17: AFIDA reports | C17: USDA FSA | D17: Ownership | E17: Structure | F17: Ownership | G17: Long-term (3-10 yrs) | H17: Official statistic | I17: 1 | J17: Annual | K17: Free download | L17: https://www.fsa.usda.gov/ | M17: Foreign holdings of US agricultural land | N17: Verify current report location before automating | O17: Original measurement | Q17: S016 | R17: Yes | S17: New data | T17: Not started | U17: Land and ownership | V17: Fetch and verify | W17: 2 | X17: Land tenure and legacy intent | Y17: Succession; Financial Analysis | Z17: Weeks to months
A18: S017 | B18: AMS Dairy Market News | C18: USDA AMS | D18: Dairy | E18: Price & market | F18: Core S&D (baseline) | G18: Near-term (1-2 seasons) | H18: Market price / trade data | I18: 2 | J18: Weekly / daily | K18: Free API (MARS) / web | L18: https://www.ams.usda.gov/market-news/dairy-market-news | M18: Prices and volumes for dry whey, WPC34/80, WPI, lactose, NDM, butter, cheese; cold storage | N18: Primary source for whey and derived dairy products | O18: Market-generated | Q18: S017 | R18: Yes | S18: Timing | T18: Not started | U18: Price and market | V18: Detection feed | W18: 2 | X18: Enterprises and income shares | Y18: Market Analysis | Z18: Minutes to hours | AA18: Wave 1
A19: S018 | B19: AMS Livestock, Poultry and Grain Market News | C19: USDA AMS | D19: Livestock & poultry | E19: Price & market | F19: Core S&D (baseline) | G19: Near-term (1-2 seasons) | H19: Market price / trade data | I19: 2 | J19: Daily / weekly | K19: Free API (MARS) / web | L19: https://www.ams.usda.gov/market-news | M19: Cash prices, boxed beef cutout, slaughter, grain bids | N19: Includes livestock mandatory reporting | O19: Market-generated | Q19: S018 | R19: Yes | S19: Timing | T19: Not started | U19: Price and market | V19: Detection feed | W19: 2 | X19: Enterprises and income shares | Y19: Market Analysis | Z19: Minutes to hours | AA19: Wave 1
A20: S019 | B20: AMS Egg Markets Overview | C20: USDA AMS | D20: Livestock & poultry | E20: Price & market | F20: Core S&D (baseline) | G20: Near-term (1-2 seasons) | H20: Market price / trade data | I20: 2 | J20: Weekly | K20: Free web | L20: https://www.ams.usda.gov/market-news | M20: Egg prices, flock and supply conditions | N20: Pairs with HPAI status from APHIS | O20: Market-generated | Q20: S019 | R20: Yes | S20: Timing | T20: Not started | U20: Price and market | V20: Detection feed | W20: 2 | X20: Enterprises and income shares | Y20: Market Analysis | Z20: Minutes to hours
A21: S020 | B21: AMS Specialty Crops Market News | C21: USDA AMS | D21: Specialty crops | E21: Price & market | F21: Core S&D (baseline) | G21: Near-term (1-2 seasons) | H21: Market price / trade data | I21: 2 | J21: Daily | K21: Free API (MARS) / web | L21: https://www.ams.usda.gov/market-news | M21: Terminal and shipping-point prices, volumes, origin | N21: Main price source for fruit and vegetables | O21: Market-generated | Q21: S020 | R21: Yes | S21: Timing | T21: Not started | U21: Price and market | V21: Detection feed | W21: 2 | X21: Enterprises and income shares | Y21: Market Analysis | Z21: Minutes to hours
A22: S021 | B22: AMS fertilizer and production cost reports | C22: USDA AMS | D22: Inputs | E22: Price & market | F22: Core S&D (baseline) | G22: Near-term (1-2 seasons) | H22: Market price / trade data | I22: 2 | J22: Bi-weekly / weekly | K22: Free web | L22: https://www.ams.usda.gov/market-news | M22: Retail and regional fertilizer prices | N22: Check which regional reports are current | O22: Market-generated | Q22: S021 | R22: Yes | S22: Timing | T22: Not started | U22: Input cost | V22: Fetch and verify | W22: 2 | X22: Cost structure and enterprises | Y22: Financial Analysis; Adoption & Efficiency | Z22: Hours to a day
A23: S022 | B23: CME dairy futures and spot | C23: CME Group | D23: Dairy | E23: Price & market | F23: Core S&D (baseline) | G23: Near-term (1-2 seasons) | H23: Market price / trade data | I23: 2 | J23: Daily | K23: Delayed free / real-time licensed | L23: https://www.cmegroup.com/markets/agriculture.html | M23: Class III and IV milk, cheese, butter, NDM, dry whey futures; forward curve | N23: Futures curve shows what the market pays to wait | O23: Market-generated | P23: S017, S006 | Q23: S022 | R23: Partial | S23: Timing | T23: Not started | U23: Price and market | V23: Detection feed | W23: 2 | X23: Enterprises and income shares | Y23: Market Analysis | Z23: Minutes to hours | AA23: Wave 2 | AB23: Confirm CME data licensing for display in a commercial product; fall back to AMS feeds
A24: S023 | B24: CME grain and livestock futures | C24: CME Group | D24: Grains & oilseeds | E24: Price & market | F24: Core S&D (baseline) | G24: Near-term (1-2 seasons) | H24: Market price / trade data | I24: 2 | J24: Daily | K24: Delayed free / real-time licensed | L24: https://www.cmegroup.com/markets/agriculture.html | M24: Corn, soy, wheat, live and feeder cattle, lean hogs | N24: Use curve shape and basis, not just front month | O24: Market-generated | P24: S001 | Q24: S023 | R24: Partial | S24: Timing | T24: Not started | U24: Price and market | V24: Detection feed | W24: 2 | X24: Enterprises and income shares | Y24: Market Analysis | Z24: Minutes to hours | AA24: Wave 2 | AB24: Confirm CME data licensing for display in a commercial product; fall back to AMS feeds
A25: S024 | B25: Global Dairy Trade auctions | C25: Global Dairy Trade | D25: Dairy | E25: Price & market | F25: Geopolitics | G25: Near-term (1-2 seasons) | H25: Market price / trade data | I25: 2 | J25: Twice monthly | K25: Free web | L25: https://www.globaldairytrade.info/ | M25: International dairy commodity price signal | N25: Reflects New Zealand, EU and other exporter supply | O25: Market-generated | Q25: S024 | R25: Yes | S25: Timing | T25: Not started | U25: Price and market | V25: Detection feed | W25: 2 | X25: Enterprises and income shares | Y25: Market Analysis | Z25: Minutes to hours | AA25: Wave 2 | AB25: Web-only; check terms and plan for licensed access or careful scraping
A26: S025 | B26: GATS (Global Agricultural Trade System) | C26: USDA FAS | D26: Cross-commodity | E26: Trade flow | F26: Geopolitics | G26: Both | H26: Official statistic | I26: 1 | J26: Monthly | K26: Free download | L26: https://apps.fas.usda.gov/gats/ | M26: US exports and imports by product (HS code), country, value and volume | N26: Confirm HS codes: whey, milk albumins and lactose sit in different chapters | O26: Derived | P26: S028 | Q26: S028 | R26: No | S26: Repackaging | T26: Not started | U26: Trade and geopolitics | V26: Fetch and verify | W26: 2 | X26: Products sold, buyers, and inputs bought | Y26: Market Analysis | Z26: Until the action changes
A27: S026 | B27: FAS Export Sales Reporting | C27: USDA FAS | D27: Grains & oilseeds | E27: Trade flow | F27: Geopolitics | G27: Near-term (1-2 seasons) | H27: Official statistic | I27: 1 | J27: Weekly | K27: Free download | L27: https://apps.fas.usda.gov/export-sales/esrd1.html | M27: Weekly commitments and shipments by destination | N27: Fast read on buyer demand, such as China and Mexico | O27: Original measurement | Q27: S026 | R27: Yes | S27: Timing | T27: Not started | U27: Trade and geopolitics | V27: Detection feed | W27: 2 | X27: Products sold, buyers, and inputs bought | Y27: Market Analysis | Z27: Until the action changes | AA27: Wave 3
A28: S027 | B28: FAS GAIN reports | C28: USDA FAS attaches | D28: Cross-commodity | E28: Trade flow | F28: Geopolitics | G28: Both | H28: Official statistic | I28: 1 | J28: Continuous | K28: Free download | L28: https://gain.fas.usda.gov/ | M28: Country-level reports on policy, crops, and market access from overseas staff | N28: One of the best on-the-ground geopolitical sources | O28: Original measurement | Q28: S027 | R28: Yes | S28: New data | T28: Not started | U28: Trade and geopolitics | V28: Detection feed | W28: 2 | X28: Products sold, buyers, and inputs bought | Y28: Market Analysis | Z28: Until the action changes
A29: S028 | B29: Census Bureau trade data | C29: US Census Bureau | D29: Cross-commodity | E29: Trade flow | F29: Geopolitics | G29: Both | H29: Official statistic | I29: 1 | J29: Monthly | K29: Free API / download | L29: https://www.census.gov/foreign-trade/index.html | M29: US trade by HS code and partner | N29: Cross-check against GATS | O29: Original measurement | Q29: S028 | R29: Yes | S29: New data | T29: Not started | U29: Trade and geopolitics | V29: Fetch and verify | W29: 2 | X29: Products sold, buyers, and inputs bought | Y29: Market Analysis | Z29: Until the action changes
A30: S029 | B30: UN Comtrade | C30: United Nations | D30: Cross-commodity | E30: Trade flow | F30: Geopolitics | G30: Long-term (3-10 yrs) | H30: Official statistic | I30: 1 | J30: Monthly / annual | K30: Free tier API / paid tiers | L30: https://comtradeplus.un.org/ | M30: Global trade flows between country pairs | N30: Needed to see competitors and third-country demand | O30: Derived | P30: S028 | Q30: S029 | R30: Partial | S30: New data | T30: Not started | U30: Trade and geopolitics | V30: Fetch and verify | W30: 2 | X30: Products sold, buyers, and inputs bought | Y30: Market Analysis | Z30: Until the action changes
A31: S030 | B31: USDEC data and analysis | C31: US Dairy Export Council | D31: Dairy | E31: Trade flow | F31: Global Affluence | G31: Both | H31: Analyst view | I31: 3 | J31: Monthly | K31: Mixed (members / public) | L31: https://www.usdec.org/ | M31: US dairy export trends by product and market | N31: Strong on whey and ingredient exports | O31: Mixed | P31: S025, S028 | Q31: S028 | R31: Partial | S31: Interpretation | T31: Not started | U31: Trade and geopolitics | V31: Context | W31: 1 | X31: Products sold, buyers, and inputs bought | Y31: Market Analysis | Z31: Until the action changes
A32: S031 | B32: FAOSTAT | C32: FAO | D32: Cross-commodity | E32: Balance sheet | F32: Core S&D (baseline) | G32: Long-term (3-10 yrs) | H32: Official statistic | I32: 1 | J32: Annual | K32: Free API / download | L32: https://www.fao.org/faostat/ | M32: Global production, trade, food balances | N32: Lags by months to a year | O32: Derived | Q32: S031 | R32: Partial | S32: New data | T32: Not started | U32: Context only | V32: Fetch and verify | W32: 2 | X32: All farms (context) | Y32: Strategic Vision; Market Analysis | Z32: Days to weeks
A33: S032 | B33: FAO Food Price Index | C33: FAO | D33: Cross-commodity | E33: Price & market | F33: Core S&D (baseline) | G33: Near-term (1-2 seasons) | H33: Official statistic | I33: 1 | J33: Monthly | K33: Free download | L33: https://www.fao.org/worldfoodsituation/foodpricesindex/en/ | M33: Global food price index by commodity group | N33: Useful global price context | O33: Derived | Q33: S032 | R33: Partial | S33: Repackaging | T33: Not started | U33: Price and market | V33: Fetch and verify | W33: 2 | X33: Enterprises and income shares | Y33: Market Analysis | Z33: Minutes to hours
A34: S033 | B34: OECD-FAO Agricultural Outlook | C34: OECD / FAO | D34: Cross-commodity | E34: Outlook | F34: Global Affluence | G34: Long-term (3-10 yrs) | H34: Analyst view | I34: 2 | J34: Annual | K34: Free download | L34: https://www.agri-outlook.org/ | M34: 10-year projections of production, use, trade, prices | N34: Baseline for long-term drivers | O34: Mixed | P34: S001, S002, S031 | Q34: S033 | R34: Partial | S34: Forecast | T34: Not started | U34: Context only | V34: Context | W34: 1 | X34: All farms (context) | Y34: Strategic Vision; Market Analysis | Z34: Days to weeks
A35: S034 | B35: FAPRI baseline | C35: University of Missouri | D35: Cross-commodity | E35: Outlook | F35: Core S&D (baseline) | G35: Long-term (3-10 yrs) | H35: Analyst view | I35: 2 | J35: Annual | K35: Free download | L35: https://www.fapri.missouri.edu/ | M35: US baseline projections and policy scenarios | N35: Good for farm bill and policy what-ifs | O35: Mixed | P35: S001, S003 | Q35: S001 | R35: Partial | S35: Forecast | T35: Not started | U35: Context only | V35: Context | W35: 1 | X35: All farms (context) | Y35: Strategic Vision; Market Analysis | Z35: Days to weeks
A36: S035 | B36: EIA weekly ethanol and energy data | C36: US EIA | D36: Grains & oilseeds | E36: Demand signal | F36: Technology | G36: Near-term (1-2 seasons) | H36: Official statistic | I36: 1 | J36: Weekly | K36: Free API | L36: https://www.eia.gov/opendata/ | M36: Ethanol production and stocks; energy prices | N36: Ethanol is a major corn demand channel | O36: Original measurement | Q36: S035 | R36: Yes | S36: Timing | T36: Not started | U36: Price and market | V36: Detection feed | W36: 2 | X36: Enterprises and income shares | Y36: Market Analysis | Z36: Minutes to hours
A37: S036 | B37: NOPA crush report | C37: National Oilseed Processors Association | D37: Grains & oilseeds | E37: Demand signal | F37: Technology | G37: Near-term (1-2 seasons) | H37: Market price / trade data | I37: 2 | J37: Monthly | K37: Free web | L37: https://www.nopa.org/ | M37: US soybean crush, meal and oil stocks | N37: Shows crush demand tied to biofuel and feed | O37: Original measurement | Q37: S036 | R37: Yes | S37: New data | T37: Not started | U37: Price and market | V37: Fetch and verify | W37: 2 | X37: Enterprises and income shares | Y37: Market Analysis | Z37: Minutes to hours
A38: S037 | B38: EPA Renewable Fuel Standard | C38: US EPA | D38: Grains & oilseeds | E38: Policy | F38: Cross-driver | G38: Both | H38: Official statistic | I38: 1 | J38: Event-driven | K38: Free web | L38: https://www.epa.gov/renewable-fuel-standard-program | M38: Biofuel blending requirements that drive soy oil and corn demand | N38: Policy changes can move demand fast | O38: Original measurement | Q38: S037 | R38: Yes | S38: New data | T38: Not started | U38: Policy and regulation | V38: Detection feed | W38: 2 | X38: Enterprises, size class, and diversification paths | Y38: Risk & Protection; Income Diversification | Z38: Until the status changes
A39: S038 | B39: CONAB crop reports | C39: Brazil CONAB | D39: Grains & oilseeds | E39: Balance sheet | F39: Core S&D (baseline) | G39: Near-term (1-2 seasons) | H39: Official statistic | I39: 1 | J39: Monthly | K39: Free download | L39: https://www.conab.gov.br/ | M39: Brazil crop estimates (soy, corn) | N39: Main competitor supply signal | O39: Original measurement | Q39: S038 | R39: Yes | S39: New data | T39: Not started | U39: Context only | V39: Fetch and verify | W39: 2 | X39: All farms (context) | Y39: Strategic Vision; Market Analysis | Z39: Days to weeks
A40: S039 | B40: Argentine grain exchange reports | C40: Buenos Aires and Rosario exchanges | D40: Grains & oilseeds | E40: Balance sheet | F40: Core S&D (baseline) | G40: Near-term (1-2 seasons) | H40: Analyst view | I40: 2 | J40: Weekly | K40: Free web | L40: https://www.bolsadecereales.com/ | M40: Argentina crop condition and estimates | N40: Spanish-language; useful for competitor supply | O40: Original measurement | Q40: S039 | R40: Yes | S40: New data | T40: Not started | U40: Context only | V40: Fetch and verify | W40: 2 | X40: All farms (context) | Y40: Strategic Vision; Market Analysis | Z40: Days to weeks
A41: S040 | B41: APHIS animal health data | C41: USDA APHIS | D41: Livestock & poultry | E41: Disease / border | F41: Geopolitics | G41: Near-term (1-2 seasons) | H41: Official statistic | I41: 1 | J41: Event-driven | K41: Free web | L41: https://www.aphis.usda.gov/ | M41: HPAI detections, animal disease status, import restrictions | N41: Disease can close markets quickly | O41: Original measurement | Q41: S040 | R41: Yes | S41: New data | T41: Not started | U41: Disease and border | V41: Detection feed | W41: 2 | X41: Location and livestock enterprises | Y41: Risk & Protection | Z41: Until the notice changes | AA41: Wave 3 | AB41: Web notices with no clear API; check terms
A42: S041 | B42: DTN retail fertilizer trends | C42: DTN | D42: Inputs | E42: Price & market | F42: Core S&D (baseline) | G42: Near-term (1-2 seasons) | H42: Market price / trade data | I42: 2 | J42: Weekly | K42: Free web | L42: https://www.dtnpf.com/ | M42: Retail fertilizer prices by product | N42: Input cost signal | O42: Market-generated | Q42: S041 | R42: Yes | S42: Timing | T42: Not started | U42: Input cost | V42: Detection feed | W42: 2 | X42: Cost structure and enterprises | Y42: Financial Analysis; Adoption & Efficiency | Z42: Hours to a day | AA42: Wave 1 | AB42: Web-only; check terms and plan for licensed access or careful scraping
A43: S042 | B43: World Bank Commodity Markets (Pink Sheet) | C43: World Bank | D43: Inputs | E43: Price & market | F43: Core S&D (baseline) | G43: Both | H43: Market price / trade data | I43: 2 | J43: Monthly | K43: Free download | L43: https://www.worldbank.org/en/research/commodity-markets | M43: Monthly global prices for fertilizer, energy, food | N43: Useful long price history | O43: Derived | Q43: S042 | R43: Partial | S43: Repackaging | T43: Not started | U43: Input cost | V43: Fetch and verify | W43: 2 | X43: Cost structure and enterprises | Y43: Financial Analysis; Adoption & Efficiency | Z43: Hours to a day
A44: S043 | B44: farmdoc daily | C44: University of Illinois | D44: Cross-commodity | E44: Analyst | F44: Core S&D (baseline) | G44: Near-term (1-2 seasons) | H44: Analyst view | I44: 3 | J44: Several per week | K44: Free web | L44: https://farmdocdaily.illinois.edu/ | M44: Practical economics, crop budgets, policy analysis | N44: High-quality extension economics | O44: Derived | P44: S001, S003, S022, S023 | Q44: S001 | R44: No | S44: Interpretation | T44: Not started | U44: Context only | V44: Context | W44: 1 | X44: All farms (context) | Y44: Strategic Vision; Market Analysis | Z44: Days to weeks
A45: S044 | B45: Iowa State Ag Decision Maker | C45: Iowa State University | D45: Cross-commodity | E45: Analyst | F45: Core S&D (baseline) | G45: Near-term (1-2 seasons) | H45: Analyst view | I45: 3 | J45: Periodic | K45: Free web | L45: https://www.extension.iastate.edu/agdm/ | M45: Farm management and market analysis | N45: Land-grant extension source | O45: Derived | P45: S001, S003 | Q45: S001 | R45: No | S45: Interpretation | T45: Not started | U45: Context only | V45: Context | W45: 1 | X45: All farms (context) | Y45: Strategic Vision; Market Analysis | Z45: Days to weeks
A46: S045 | B46: Purdue Ag Economy Barometer | C46: Purdue / CME Group | D46: Farm economy | E46: Analyst | F46: Ownership | G46: Near-term (1-2 seasons) | H46: Analyst view | I46: 3 | J46: Monthly | K46: Free web | L46: https://ag.purdue.edu/commercialag/ageconomybarometer/ | M46: Farmer sentiment on investment, finance, land | N46: Survey of producers | O46: Original measurement | Q46: S045 | R46: Yes | S46: New data | T46: Not started | U46: Context only | V46: Context | W46: 1 | X46: All farms (context) | Y46: Strategic Vision; Market Analysis | Z46: Days to weeks
A47: S046 | B47: Kansas City Fed ag credit surveys | C47: Federal Reserve Bank of Kansas City | D47: Farm economy | E47: Economy | F47: Ownership | G47: Near-term (1-2 seasons) | H47: Official statistic | I47: 1 | J47: Quarterly | K47: Free web | L47: https://www.kansascityfed.org/agriculture/ag-credit-surveys/ | M47: Farm credit conditions, land values, interest rates | N47: Regional ag banker survey | O47: Original measurement | Q47: S046 | R47: Yes | S47: New data | T47: Not started | U47: Credit and finance | V47: Fetch and verify | W47: 2 | X47: Debt and financial health | Y47: Financial Analysis; Risk & Protection | Z47: Days to weeks
A48: S047 | B48: Chicago Fed AgLetter | C48: Federal Reserve Bank of Chicago | D48: Farm economy | E48: Economy | F48: Ownership | G48: Near-term (1-2 seasons) | H48: Official statistic | I48: 1 | J48: Quarterly | K48: Free web | L48: https://www.chicagofed.org/publications/agletter/index | M48: Land values and credit in the Seventh District | N48: Verify current page address | O48: Original measurement | Q48: S047 | R48: Yes | S48: New data | T48: Not started | U48: Credit and finance | V48: Fetch and verify | W48: 2 | X48: Debt and financial health | Y48: Financial Analysis; Risk & Protection | Z48: Days to weeks
A49: S048 | B49: RaboResearch (dairy, grains, animal protein, fresh produce) | C49: Rabobank | D49: Cross-commodity | E49: Analyst | F49: Global Affluence | G49: Both | H49: Analyst view | I49: 3 | J49: Quarterly | K49: Mixed (some paywalled) | L49: https://research.rabobank.com/ | M49: Global sector outlooks and thematic reports | N49: Top interpretation layer; confirm access level | O49: Mixed | P49: S001, S003, S025, S022, S024 | Q49: S048 | R49: Partial | S49: Forecast | T49: Not started | U49: Context only | V49: Context | W49: 1 | X49: All farms (context) | Y49: Strategic Vision; Market Analysis | Z49: Days to weeks
A50: S049 | B50: LMIC (Livestock Marketing Information Center) | C50: LMIC | D50: Livestock & poultry | E50: Analyst | F50: Core S&D (baseline) | G50: Near-term (1-2 seasons) | H50: Analyst view | I50: 3 | J50: Periodic | K50: Paid | L50: https://lmic.info/ | M50: Livestock, meat and dairy market analysis | N50: Subscription | O50: Mixed | P50: S001, S005, S018 | Q50: S049 | R50: Partial | S50: Forecast | T50: Not started | U50: Context only | V50: Context | W50: 1 | X50: All farms (context) | Y50: Strategic Vision; Market Analysis | Z50: Days to weeks
A51: S050 | B51: CattleFax | C51: CattleFax | D51: Livestock & poultry | E51: Analyst | F51: Core S&D (baseline) | G51: Near-term (1-2 seasons) | H51: Analyst view | I51: 3 | J51: Weekly / periodic | K51: Paid | L51: https://www.cattlefax.com/ | M51: Cattle market outlook and data | N51: Subscription | O51: Mixed | P51: S005, S018, S023 | Q51: S050 | R51: Partial | S51: Forecast | T51: Not started | U51: Context only | V51: Context | W51: 1 | X51: All farms (context) | Y51: Strategic Vision; Market Analysis | Z51: Days to weeks
A52: S051 | B52: IDFA and NMPF industry analysis | C52: IDFA / NMPF | D52: Dairy | E52: Analyst | F52: Human Health | G52: Both | H52: Analyst view | I52: 3 | J52: Periodic | K52: Free web | L52: https://www.idfa.org/ | M52: Dairy processor and producer policy and market views | N52: Advocacy sources; label as such | O52: Opinion | P52: S006, S017, S025 | Q52: S006 | R52: No | S52: Interpretation | T52: Not started | U52: Context only | V52: Context | W52: 1 | X52: All farms (context) | Y52: Strategic Vision; Market Analysis | Z52: Days to weeks
A53: S052 | B53: IMF World Economic Outlook | C53: IMF | D53: Cross-commodity | E53: Outlook | F53: Global Affluence | G53: Long-term (3-10 yrs) | H53: Analyst view | I53: 2 | J53: Twice yearly | K53: Free download / API | L53: https://www.imf.org/en/Publications/WEO | M53: Global growth and inflation forecasts | N53: Macro backdrop | O53: Mixed | Q53: S052 | R53: Yes | S53: Forecast | T53: Not started | U53: Context only | V53: Context | W53: 1 | X53: All farms (context) | Y53: Strategic Vision; Market Analysis | Z53: Days to weeks
A54: S053 | B54: World Bank Open Data | C54: World Bank | D54: Cross-commodity | E54: Outlook | F54: Global Affluence | G54: Long-term (3-10 yrs) | H54: Official statistic | I54: 1 | J54: Annual | K54: Free API | L54: https://data.worldbank.org/ | M54: Income, population, urbanization by country | N54: Demand-side indicators | O54: Derived | Q54: S053 | R54: Partial | S54: Repackaging | T54: Not started | U54: Context only | V54: Context | W54: 1 | X54: All farms (context) | Y54: Strategic Vision; Market Analysis | Z54: Days to weeks
A55: S054 | B55: USTR trade actions | C55: US Trade Representative | D55: Cross-commodity | E55: Policy | F55: Geopolitics | G55: Both | H55: Official statistic | I55: 1 | J55: Event-driven | K55: Free web | L55: https://ustr.gov/ | M55: Tariffs, trade agreements, investigations | N55: Monitor for market access changes | O55: Original measurement | Q55: S054 | R55: Yes | S55: New data | T55: Not started | U55: Trade and geopolitics | V55: Detection feed | W55: 2 | X55: Products sold, buyers, and inputs bought | Y55: Market Analysis | Z55: Until the action changes
A56: S055 | B56: WTO data and notifications | C56: World Trade Organization | D56: Cross-commodity | E56: Policy | F56: Geopolitics | G56: Long-term (3-10 yrs) | H56: Official statistic | I56: 1 | J56: Event-driven | K56: Free web | L56: https://www.wto.org/ | M56: Tariff schedules, disputes, SPS/TBT notifications | N56: Non-tariff barriers show up here | O56: Original measurement | Q56: S055 | R56: Yes | S56: New data | T56: Not started | U56: Trade and geopolitics | V56: Detection feed | W56: 2 | X56: Products sold, buyers, and inputs bought | Y56: Market Analysis | Z56: Until the action changes
A57: S056 | B57: Global Trade Alert | C57: St. Gallen | D57: Cross-commodity | E57: Policy | F57: Geopolitics | G57: Near-term (1-2 seasons) | H57: Analyst view | I57: 2 | J57: Continuous | K57: Free web | L57: https://www.globaltradealert.org/ | M57: Tracker of trade policy interventions worldwide | N57: Independent policy tracker | O57: Mixed | P57: S054, S057 | Q57: S056 | R57: Partial | S57: Timing | T57: Not started | U57: Trade and geopolitics | V57: Detection feed | W57: 2 | X57: Products sold, buyers, and inputs bought | Y57: Market Analysis | Z57: Until the action changes | AA57: Wave 3 | AB57: Check terms and data export options
A58: S057 | B58: Federal Register | C58: US Government | D58: Cross-commodity | E58: Policy | F58: Cross-driver | G58: Both | H58: Official statistic | I58: 1 | J58: Daily | K58: Free API | L58: https://www.federalregister.gov/ | M58: Proposed and final rules from USDA, FDA, EPA, USTR | N58: Use API keyword alerts | O58: Original measurement | Q58: S057 | R58: Yes | S58: Timing | T58: Not started | U58: Policy and regulation | V58: Detection feed | W58: 2 | X58: Enterprises, size class, and diversification paths | Y58: Risk & Protection; Income Diversification | Z58: Until the status changes | AA58: Wave 1
A59: S058 | B59: ACLED | C59: ACLED | D59: Cross-commodity | E59: Policy | F59: Geopolitics | G59: Near-term (1-2 seasons) | H59: Analyst view | I59: 2 | J59: Weekly | K59: Free for registered users | L59: https://acleddata.com/ | M59: Conflict events affecting ports, routes, producers | N59: Check terms of use | O59: Original measurement | Q59: S058 | R59: Yes | S59: New data | T59: Not started | U59: Trade and geopolitics | V59: Detection feed | W59: 2 | X59: Products sold, buyers, and inputs bought | Y59: Market Analysis | Z59: Until the action changes
A60: S059 | B60: Dietary Guidelines for Americans | C60: USDA / HHS | D60: Dairy | E60: Policy | F60: Human Health | G60: Long-term (3-10 yrs) | H60: Official statistic | I60: 1 | J60: Every 5 years | K60: Free web | L60: https://www.dietaryguidelines.gov/ | M60: Federal dietary guidance that shapes school meals and programs | N60: Slow but structural demand driver | O60: Original measurement | Q60: S059 | R60: Yes | S60: New data | T60: Not started | U60: Policy and regulation | V60: Fetch and verify | W60: 2 | X60: Enterprises, size class, and diversification paths | Y60: Risk & Protection; Income Diversification | Z60: Until the status changes
A61: S060 | B61: FDA food regulation and approvals | C61: US FDA | D61: Cross-commodity | E61: Policy | F61: Human Health | G61: Both | H61: Official statistic | I61: 1 | J61: Event-driven | K61: Free web | L61: https://www.fda.gov/food | M61: Labeling, ingredient safety, novel food and GRAS decisions | N61: Tracks precision fermentation and new proteins | O61: Original measurement | Q61: S060 | R61: Yes | S61: New data | T61: Not started | U61: Policy and regulation | V61: Detection feed | W61: 2 | X61: Enterprises, size class, and diversification paths | Y61: Risk & Protection; Income Diversification | Z61: Until the status changes
A62: S061 | B62: CDC nutrition and obesity data | C62: US CDC | D62: Cross-commodity | E62: Demand signal | F62: Human Health | G62: Long-term (3-10 yrs) | H62: Official statistic | I62: 1 | J62: Periodic | K62: Free download | L62: https://www.cdc.gov/ | M62: Diet and health trends | N62: Context for protein and GLP-1 related demand shifts | O62: Original measurement | Q62: S061 | R62: Yes | S62: New data | T62: Not started | U62: Context only | V62: Fetch and verify | W62: 2 | X62: All farms (context) | Y62: Strategic Vision; Market Analysis | Z62: Days to weeks
A63: S062 | B63: IFIC Food and Health Survey | C63: International Food Information Council | D63: Cross-commodity | E63: Demand signal | F63: Human Health | G63: Both | H63: Analyst view | I63: 3 | J63: Annual | K63: Free web | L63: https://foodinsight.org/ | M63: Consumer attitudes on protein, ingredients, health | N63: Survey-based; note sample and sponsor | O63: Original measurement | Q63: S062 | R63: Yes | S63: New data | T63: Not started | U63: Context only | V63: Fetch and verify | W63: 2 | X63: All farms (context) | Y63: Strategic Vision; Market Analysis | Z63: Days to weeks
A64: S063 | B64: Circana and NielsenIQ retail data | C64: Circana / NielsenIQ | D64: Cross-commodity | E64: Demand signal | F64: Human Health | G64: Near-term (1-2 seasons) | H64: Market price / trade data | I64: 2 | J64: Weekly / monthly | K64: Paid | L64: https://www.circana.com/ | M64: Retail sales volume and price by category | N64: Strong demand signal; subscription | O64: Original measurement | Q64: S063 | R64: Yes | S64: New data | T64: Not started | U64: Context only | V64: Fetch and verify | W64: 2 | X64: All farms (context) | Y64: Strategic Vision; Market Analysis | Z64: Days to weeks
A65: S064 | B65: NOAA Climate Prediction Center | C65: NOAA | D65: Cross-commodity | E65: Weather | F65: Climate Volatility | G65: Near-term (1-2 seasons) | H65: Official statistic | I65: 1 | J65: Weekly / monthly | K65: Free download | L65: https://www.cpc.ncep.noaa.gov/ | M65: Seasonal temperature and precipitation outlooks, ENSO status | N65: Core near-term weather layer | O65: Original measurement | Q65: S064 | R65: Yes | S65: Forecast | T65: Not started | U65: Weather and climate | V65: Detection feed | W65: 2 | X65: Location and operation characteristics (soil, water, climate zone) | Y65: Risk & Protection | Z65: Hours to a day
A66: S065 | B66: US Drought Monitor | C66: NDMC / USDA / NOAA | D66: Cross-commodity | E66: Weather | F66: Climate Volatility | G66: Near-term (1-2 seasons) | H66: Official statistic | I66: 1 | J66: Weekly | K66: Free download / API | L66: https://droughtmonitor.unl.edu/ | M66: Drought severity by county | N66: Map to farm location | O66: Mixed | P66: S064 | Q66: S065 | R66: Partial | S66: Interpretation | T66: Not started | U66: Weather and climate | V66: Detection feed | W66: 2 | X66: Location and operation characteristics (soil, water, climate zone) | Y66: Risk & Protection | Z66: Hours to a day | AA66: Wave 1
A67: S066 | B67: Copernicus Climate Change Service | C67: ECMWF | D67: Cross-commodity | E67: Weather | F67: Climate Volatility | G67: Both | H67: Official statistic | I67: 1 | J67: Monthly | K67: Free API | L67: https://climate.copernicus.eu/ | M67: Global climate data and seasonal forecasts | N67: Good for non-US producer regions | O67: Original measurement | Q67: S066 | R67: Yes | S67: Forecast | T67: Not started | U67: Weather and climate | V67: Fetch and verify | W67: 2 | X67: Location and operation characteristics (soil, water, climate zone) | Y67: Risk & Protection | Z67: Hours to a day
A68: S067 | B68: FAO GIEWS and FEWS NET | C68: FAO / USAID-origin network | D68: Cross-commodity | E68: Weather | F68: Climate Volatility | G68: Near-term (1-2 seasons) | H68: Official statistic | I68: 1 | J68: Monthly | K68: Free web | L68: https://www.fao.org/giews/ | M68: Crop prospects and food security alerts | N68: Confirm FEWS NET availability and hosting before relying on it | O68: Mixed | P68: S064, S066, S038 | Q68: S067 | R68: Partial | S68: Interpretation | T68: Not started | U68: Weather and climate | V68: Fetch and verify | W68: 2 | X68: Location and operation characteristics (soil, water, climate zone) | Y68: Risk & Protection | Z68: Hours to a day
A69: S068 | B69: USDA Risk Management Agency | C69: USDA RMA | D69: Cross-commodity | E69: Economy | F69: Climate Volatility | G69: Near-term (1-2 seasons) | H69: Official statistic | I69: 1 | J69: Annual | K69: Free download | L69: https://www.rma.usda.gov/ | M69: Crop insurance participation, indemnities, rates | N69: Shows where weather losses concentrate | O69: Original measurement | Q69: S068 | R69: Yes | S69: New data | T69: Not started | U69: Weather and climate | V69: Fetch and verify | W69: 2 | X69: Location and operation characteristics (soil, water, climate zone) | Y69: Risk & Protection | Z69: Hours to a day
A70: S069 | B70: USPTO PatentsView | C70: USPTO | D70: Cross-commodity | E70: Technology | F70: Technology | G70: Long-term (3-10 yrs) | H70: Official statistic | I70: 1 | J70: Quarterly | K70: Free API | L70: https://patentsview.org/ | M70: Patent filings in ag, food, fermentation, genetics | N70: Leading indicator of technology shifts | O70: Derived | Q70: S069 | R70: Yes | S70: New data | T70: Not started | U70: Technology and structure | V70: Fetch and verify | W70: 2 | X70: Goals, adoption plans, and competitive advantage | Y70: Adoption & Efficiency; Competitive Advantage | Z70: Weeks
A71: S070 | B71: AgFunder research and news | C71: AgFunder | D71: Cross-commodity | E71: Technology | F71: Technology | G71: Both | H71: Analyst view | I71: 3 | J71: Periodic | K71: Free web | L71: https://agfundernews.com/ | M71: Ag and food tech investment trends | N71: Investment is a signal, not proof of adoption | O71: Mixed | Q71: S070 | R71: Yes | S71: Interpretation | T71: Not started | U71: Technology and structure | V71: Context | W71: 1 | X71: Goals, adoption plans, and competitive advantage | Y71: Adoption & Efficiency; Competitive Advantage | Z71: Weeks
A72: S071 | B72: DOJ Antitrust and FTC actions | C72: US DOJ / FTC | D72: Cross-commodity | E72: Structure | F72: Ownership | G72: Both | H72: Official statistic | I72: 1 | J72: Event-driven | K72: Free web | L72: https://www.justice.gov/atr | M72: Merger reviews and competition actions in food and ag | N72: Consolidation and market power signals | O72: Original measurement | Q72: S071 | R72: Yes | S72: New data | T72: Not started | U72: Technology and structure | V72: Fetch and verify | W72: 2 | X72: Goals, adoption plans, and competitive advantage | Y72: Adoption & Efficiency; Competitive Advantage | Z72: Weeks
A73: S072 | B73: Congress.gov | C73: Library of Congress | D73: Cross-commodity | E73: Policy | F73: Cross-driver | G73: Both | H73: Official record | I73: 1 | J73: Daily | K73: Free web / API | L73: https://www.congress.gov/ | M73: Bill text, status, sponsors, amendments, including farm bill, appropriations and trade bills | N73: Primary legislative record; API available | O73: Original measurement | Q73: S072 | R73: Yes | S73: Timing | T73: Not started | U73: Policy and regulation | V73: Detection feed | W73: 2 | X73: Enterprises, size class, and diversification paths | Y73: Risk & Protection; Income Diversification | Z73: Until the status changes | AA73: Wave 2
A74: S073 | B74: House and Senate Agriculture Committees | C74: US Congress | D74: Cross-commodity | E74: Policy | F74: Cross-driver | G74: Both | H74: Official record | I74: 1 | J74: Event-driven | K74: Free web | L74: https://agriculture.house.gov/ | M74: Farm bill hearings, markups, committee reports, jurisdiction over farm programs | N74: Senate site: agriculture.senate.gov | O74: Original measurement | Q74: S073 | R74: Yes | S74: Timing | T74: Not started | U74: Policy and regulation | V74: Detection feed | W74: 2 | X74: Enterprises, size class, and diversification paths | Y74: Risk & Protection; Income Diversification | Z74: Until the status changes
A75: S074 | B75: CRS reports on agriculture policy | C75: Congressional Research Service | D75: Cross-commodity | E75: Policy | F75: Cross-driver | G75: Both | H75: Official record | I75: 1 | J75: Periodic | K75: Free web | L75: https://crsreports.congress.gov/ | M75: Nonpartisan explainers of farm programs, trade, food safety and regulation | N75: Good for how a rule or program works | O75: Derived | P75: S072 | Q75: S072 | R75: No | S75: Interpretation | T75: Not started | U75: Policy and regulation | V75: Context | W75: 1 | X75: Enterprises, size class, and diversification paths | Y75: Risk & Protection; Income Diversification | Z75: Until the status changes
A76: S075 | B76: CBO baseline and farm program cost estimates | C76: Congressional Budget Office | D76: Cross-commodity | E76: Policy | F76: Cross-driver | G76: Both | H76: Official record | I76: 1 | J76: Annual / event-driven | K76: Free download | L76: https://www.cbo.gov/ | M76: Projected spending on commodity programs, crop insurance, nutrition; cost of bills | N76: Shows what policy changes cost and when | O76: Mixed | Q76: S075 | R76: Partial | S76: Forecast | T76: Not started | U76: Policy and regulation | V76: Context | W76: 1 | X76: Enterprises, size class, and diversification paths | Y76: Risk & Protection; Income Diversification | Z76: Until the status changes
A77: S076 | B77: Regulations.gov dockets | C77: US Government | D77: Cross-commodity | E77: Policy | F77: Cross-driver | G77: Both | H77: Official record | I77: 1 | J77: Daily | K77: Free web / API | L77: https://www.regulations.gov/ | M77: Proposed rules, public comments, final rule dockets from USDA, EPA, FDA, DOL | N77: Comment periods are early warning of rule changes | O77: Original measurement | Q77: S076 | R77: Yes | S77: Timing | T77: Not started | U77: Policy and regulation | V77: Detection feed | W77: 2 | X77: Enterprises, size class, and diversification paths | Y77: Risk & Protection; Income Diversification | Z77: Until the status changes
A78: S077 | B78: Unified Agenda and OIRA review | C78: Office of Management and Budget | D78: Cross-commodity | E78: Policy | F78: Cross-driver | G78: Both | H78: Official record | I78: 1 | J78: Twice yearly / continuous | K78: Free web | L78: https://www.reginfo.gov/public/do/eAgendaMain | M78: Rules planned and under White House review, with expected timing | N78: Earliest public signal that a rule is coming | O78: Original measurement | Q78: S077 | R78: Yes | S78: Timing | T78: Not started | U78: Policy and regulation | V78: Fetch and verify | W78: 2 | X78: Enterprises, size class, and diversification paths | Y78: Risk & Protection; Income Diversification | Z78: Until the status changes
A79: S078 | B79: USDA FSA program notices | C79: USDA Farm Service Agency | D79: Cross-commodity | E79: Policy | F79: Cross-driver | G79: Both | H79: Official record | I79: 1 | J79: Event-driven | K79: Free web | L79: https://www.fsa.usda.gov/resources/programs | M79: ARC/PLC, Dairy Margin Coverage, disaster aid, loan programs, sign-up dates | N79: Program rules and deadlines that affect farm income | O79: Original measurement | Q79: S078 | R79: Yes | S79: New data | T79: Not started | U79: Policy and regulation | V79: Detection feed | W79: 2 | X79: Enterprises, size class, and diversification paths | Y79: Risk & Protection; Income Diversification | Z79: Until the status changes
A80: S079 | B80: Federal Milk Marketing Orders | C80: USDA AMS | D80: Dairy | E80: Policy | F80: Cross-driver | G80: Both | H80: Official record | I80: 1 | J80: Event-driven | K80: Free web | L80: https://www.ams.usda.gov/rules-regulations/moa/dairy | M80: Milk pricing formulas, hearings, decisions, and amendments | N80: Direct driver of the milk check; confirm current page address | O80: Original measurement | Q80: S079 | R80: Yes | S80: New data | T80: Not started | U80: Policy and regulation | V80: Detection feed | W80: 2 | X80: Enterprises, size class, and diversification paths | Y80: Risk & Protection; Income Diversification | Z80: Until the status changes
A81: S080 | B81: AMS marketing orders and agreements | C81: USDA AMS | D81: Specialty crops | E81: Policy | F81: Cross-driver | G81: Both | H81: Official record | I81: 1 | J81: Event-driven | K81: Free web | L81: https://www.ams.usda.gov/rules-regulations/moa | M81: Fruit, vegetable, nut and milk marketing orders; research and promotion programs | N81: Rules that shape volumes, quality and promotion | O81: Original measurement | Q81: S080 | R81: Yes | S81: New data | T81: Not started | U81: Policy and regulation | V81: Detection feed | W81: 2 | X81: Enterprises, size class, and diversification paths | Y81: Risk & Protection; Income Diversification | Z81: Until the status changes
A82: S081 | B82: Packers and Stockyards Act rules and enforcement | C82: USDA AMS | D82: Livestock & poultry | E82: Policy | F82: Cross-driver | G82: Both | H82: Official record | I82: 1 | J82: Event-driven | K82: Free web | L82: https://www.ams.usda.gov/rules-regulations/packers-and-stockyards-act | M82: Contracting, pricing transparency and competition rules for livestock and poultry | N82: Confirm current page address | O82: Original measurement | Q82: S081 | R82: Yes | S82: New data | T82: Not started | U82: Policy and regulation | V82: Detection feed | W82: 2 | X82: Enterprises, size class, and diversification paths | Y82: Risk & Protection; Income Diversification | Z82: Until the status changes
A83: S082 | B83: FSIS rules, labeling and inspection policy | C83: USDA FSIS | D83: Livestock & poultry | E83: Policy | F83: Cross-driver | G83: Both | H83: Official record | I83: 1 | J83: Event-driven | K83: Free web | L83: https://www.fsis.usda.gov/policy | M83: Meat, poultry and egg product inspection, line speeds, origin and product labeling | N83: Covers processing and labeling that sets market access | O83: Original measurement | Q83: S082 | R83: Yes | S83: New data | T83: Not started | U83: Policy and regulation | V83: Detection feed | W83: 2 | X83: Enterprises, size class, and diversification paths | Y83: Risk & Protection; Income Diversification | Z83: Until the status changes
A84: S083 | B84: APHIS regulations (animal disease, plant health, biotechnology) | C84: USDA APHIS | D84: Cross-commodity | E84: Policy | F84: Cross-driver | G84: Both | H84: Official record | I84: 1 | J84: Event-driven | K84: Free web | L84: https://www.aphis.usda.gov/ | M84: Disease control rules, import and movement restrictions, biotech crop and organism regulation | N84: See the regulations and policies sections; confirm deep links | O84: Original measurement | Q84: S083 | R84: Yes | S84: New data | T84: Not started | U84: Disease and border | V84: Detection feed | W84: 2 | X84: Location and livestock enterprises | Y84: Risk & Protection | Z84: Until the notice changes
A85: S084 | B85: FDA Food Safety Modernization Act rules | C85: US FDA | D85: Specialty crops | E85: Policy | F85: Cross-driver | G85: Both | H85: Official record | I85: 1 | J85: Event-driven | K85: Free web | L85: https://www.fda.gov/food/guidance-regulation-food-and-dietary-supplements/food-safety-modernization-act-fsma | M85: Produce safety, preventive controls, traceability requirements | N85: Compliance cost and market access for produce and processors | O85: Original measurement | Q85: S084 | R85: Yes | S85: New data | T85: Not started | U85: Policy and regulation | V85: Detection feed | W85: 2 | X85: Enterprises, size class, and diversification paths | Y85: Risk & Protection; Income Diversification | Z85: Until the status changes
A86: S085 | B86: EPA pesticide program | C86: US EPA | D86: Cross-commodity | E86: Policy | F86: Cross-driver | G86: Both | H86: Official record | I86: 1 | J86: Event-driven | K86: Free web | L86: https://www.epa.gov/pesticides | M86: Pesticide registrations, label changes, endangered species measures, residue tolerances | N86: Affects crop protection options and residue limits | O86: Original measurement | Q86: S085 | R86: Yes | S86: New data | T86: Not started | U86: Policy and regulation | V86: Detection feed | W86: 2 | X86: Enterprises, size class, and diversification paths | Y86: Risk & Protection; Income Diversification | Z86: Until the status changes
A87: S086 | B87: EPA agriculture and water, air and nutrient rules | C87: US EPA | D87: Cross-commodity | E87: Policy | F87: Cross-driver | G87: Both | H87: Official record | I87: 1 | J87: Event-driven | K87: Free web | L87: https://www.epa.gov/agriculture | M87: Water and air rules, manure and nutrient management, large livestock operations | N87: Environmental compliance for crop and livestock farms | O87: Original measurement | Q87: S086 | R87: Yes | S87: New data | T87: Not started | U87: Policy and regulation | V87: Detection feed | W87: 2 | X87: Enterprises, size class, and diversification paths | Y87: Risk & Protection; Income Diversification | Z87: Until the status changes
... A91: S090 | B91: IRS and Treasury guidance for farms | C91: IRS / US Treasury | D91: Cross-commodity | E91: Policy | F91: Cross-driver | G91: Both | H91: Official record | I91: 1 | J91: Event-driven | K91: Free web | L91: https://www.irs.gov/ | M91: Tax treatment of farm income, equipment, estates, and clean fuel credits | N91: Verify specific guidance pages; top-level link given | O91: Original measurement | Q91: S090 | R91: Yes | S91: New data | T91: Not started | U91: Policy and regulation | V91: Detection feed | W91: 2 | X91: Enterprises, size class, and diversification paths | Y91: Risk & Protection; Income Diversification | Z91: Until the status changes
A92: S091 | B92: ERS Farm and Commodity Policy | C92: USDA ERS | D92: Cross-commodity | E92: Policy | F92: Cross-driver | G92: Both | H92: Official record | I92: 1 | J92: Periodic | K92: Free web | L92: https://www.ers.usda.gov/topics/farm-economy/farm-commodity-policy/ | M92: Explanations of farm programs, payments, and policy changes | N92: Confirm current page address | O92: Derived | P92: S072 | Q92: S072 | R92: No | S92: Interpretation | T92: Not started | U92: Policy and regulation | V92: Context | W92: 1 | X92: Enterprises, size class, and diversification paths | Y92: Risk & Protection; Income Diversification | Z92: Until the status changes
A93: S092 | B93: NCSL agriculture and rural development tracker | C93: National Conference of State Legislatures | D93: Cross-commodity | E93: Policy | F93: Cross-driver | G93: Both | H93: Analyst view | I93: 2 | J93: Periodic | K93: Free web | L93: https://www.ncsl.org/agriculture-and-rural-development | M93: State legislation summaries on agriculture, food, land and labor | N93: State-level view; summaries, not bill text | O93: Derived | Q93: S092 | R93: Partial | S93: Repackaging | T93: Not started | U93: Policy and regulation | V93: Context | W93: 1 | X93: Location (state) and enterprises | Y93: Risk & Protection; Income Diversification | Z93: Until the status changes
A94: S093 | B94: LegiScan | C94: LegiScan | D94: Cross-commodity | E94: Policy | F94: Cross-driver | G94: Both | H94: Analyst view | I94: 2 | J94: Daily | K94: Free tier / paid API | L94: https://legiscan.com/ | M94: Bill text and status across all 50 state legislatures | N94: Best for keyword alerts on state bills | O94: Derived | Q94: S093 | R94: Partial | S94: Timing | T94: Not started | U94: Policy and regulation | V94: Detection feed | W94: 2 | X94: Location (state) and enterprises | Y94: Risk & Protection; Income Diversification | Z94: Until the status changes | AA94: Wave 2 | AB94: Free tier has limits
A95: S094 | B95: NASDA | C95: National Association of State Departments of Agriculture | D95: Cross-commodity | E95: Policy | F95: Cross-driver | G95: Both | H95: Analyst view | I95: 3 | J95: Periodic | K95: Free web | L95: https://www.nasda.org/ | M95: State agriculture department positions and policy priorities | N95: Association view; label as such | O95: Mixed | Q95: S094 | R95: Partial | S95: Interpretation | T95: Not started | U95: Policy and regulation | V95: Context | W95: 1 | X95: Location (state) and enterprises | Y95: Risk & Protection; Income Diversification | Z95: Until the status changes
A96: S095 | B96: National Agricultural Law Center | C96: University of Arkansas | D96: Cross-commodity | E96: Policy | F96: Cross-driver | G96: Both | H96: Analyst view | I96: 2 | J96: Periodic | K96: Free web | L96: https://nationalaglawcenter.org/ | M96: Plain-language legal analysis of farm law, state laws and court decisions | N96: Strong on state law and litigation | O96: Derived | P96: S072, S076 | Q96: S072 | R96: Partial | S96: Interpretation | T96: Not started | U96: Policy and regulation | V96: Context | W96: 1 | X96: Enterprises, size class, and diversification paths | Y96: Risk & Protection; Income Diversification | Z96: Until the status changes
A97: S096 | B97: Ballotpedia agriculture ballot measures | C97: Ballotpedia | D97: Livestock & poultry | E97: Policy | F97: Cross-driver | G97: Both | H97: Analyst view | I97: 2 | J97: Event-driven | K97: Free web | L97: https://ballotpedia.org/ | M97: State ballot measures on animal welfare, food and farming | N97: Animal welfare measures have changed livestock and egg rules | O97: Derived | Q97: S096 | R97: Partial | S97: Timing | T97: Not started | U97: Policy and regulation | V97: Detection feed | W97: 2 | X97: Location (state) and enterprises | Y97: Risk & Protection; Income Diversification | Z97: Until the status changes
A98: S097 | B98: USITC tariff schedule (HTS) and trade remedies | C98: US International Trade Commission | D98: Cross-commodity | E98: Policy | F98: Geopolitics | G98: Both | H98: Official record | I98: 1 | J98: Event-driven | K98: Free web | L98: https://hts.usitc.gov/ | M98: Tariff rates by product code, trade remedy cases | N98: Pairs with trade data by HS code | O98: Original measurement | Q98: S097 | R98: Yes | S98: New data | T98: Not started | U98: Trade and geopolitics | V98: Detection feed | W98: 2 | X98: Products sold, buyers, and inputs bought | Y98: Market Analysis | Z98: Until the action changes
A99: S098 | B99: Commerce AD/CVD enforcement | C99: US Department of Commerce | D99: Inputs | E99: Policy | F99: Geopolitics | G99: Both | H99: Official record | I99: 1 | J99: Event-driven | K99: Free web | L99: https://www.trade.gov/enforcement-and-compliance | M99: Antidumping and countervailing duty cases on imports, including fertilizer and produce | N99: Confirm current page address | O99: Original measurement | Q99: S098 | R99: Yes | S99: New data | T99: Not started | U99: Trade and geopolitics | V99: Detection feed | W99: 2 | X99: Products sold, buyers, and inputs bought | Y99: Market Analysis | Z99: Until the action changes
A100: S099 | B100: EU Common Agricultural Policy and EUR-Lex | C100: European Commission | D100: Cross-commodity | E100: Policy | F100: Geopolitics | G100: Both | H100: Official record | I100: 1 | J100: Event-driven | K100: Free web | L100: https://agriculture.ec.europa.eu/ | M100: EU farm policy, import standards, deforestation and sustainability rules affecting exports | N100: EUR-Lex holds the legal texts | O100: Original measurement | Q100: S099 | R100: Yes | S100: New data | T100: Not started | U100: Trade and geopolitics | V100: Detection feed | W100: 2 | X100: Products sold, buyers, and inputs bought | Y100: Market Analysis | Z100: Until the action changes
A101: S100 | B101: Codex Alimentarius | C101: FAO / WHO | D101: Cross-commodity | E101: Policy | F101: Geopolitics | G101: Both | H101: Official record | I101: 1 | J101: Periodic | K101: Free web | L101: https://www.fao.org/fao-who-codexalimentarius/ | M101: International food standards, residue limits, labeling guidance | N101: Reference standards behind many import rules | O101: Original measurement | Q101: S100 | R101: Yes | S101: New data | T101: Not started | U101: Trade and geopolitics | V101: Fetch and verify | W101: 2 | X101: Products sold, buyers, and inputs bought | Y101: Market Analysis | Z101: Until the action changes
A102: S101 | B102: WOAH animal health standards and disease reports | C102: World Organisation for Animal Health | D102: Livestock & poultry | E102: Policy | F102: Geopolitics | G102: Both | H102: Official record | I102: 1 | J102: Event-driven | K102: Free web | L102: https://www.woah.org/ | M102: Animal disease reporting and trade standards that trigger import bans | N102: Disease status drives market access | O102: Original measurement | Q102: S101 | R102: Yes | S102: Timing | T102: Not started | U102: Disease and border | V102: Detection feed | W102: 2 | X102: Location and livestock enterprises | Y102: Risk & Protection | Z102: Until the notice changes
A103: S102 | B103: National Corn Growers Association | C103: NCGA | D103: Grains & oilseeds | E103: Policy | F103: Cross-driver | G103: Both | H103: Analyst view | I103: 3 | J103: Periodic | K103: Free web | L103: https://www.ncga.com/ | M103: Corn policy positions on farm bill, biofuels, trade | N103: Advocacy; label as such | O103: Opinion | Q103: S057 | R103: No | S103: Interpretation | T103: Not started | U103: Policy and regulation | V103: Context | W103: 1 | X103: Enterprises, size class, and diversification paths | Y103: Risk & Protection; Income Diversification | Z103: Until the status changes
...

Sheet MVP Sources
A1: MVP sources: the first 15, by build wave
A2: Chosen for dynamic sources and authority tier 2 where it exists. Wave is set in the Source Registry (MVP wave column); this tab reads from it.
A4: Wave | B4: ID | C4: Source | D4: Authority tier | E4: Cadence | F4: Trigger family | G4: System role | H4: Access | I4: Watch-out before building
A5: =IFERROR(INDEX('Source Registry'!$AA$2:$AA$400,MATCH($B5,'Source Registry'!$A$2:$A$400,0))&"","") -> Wave 1 | B5: S018 | C5: =IFERROR(INDEX('Source Registry'!$B$2:$B$400,MATCH($B5,'Source Registry'!$A$2:$A$400,0))&"","") -> AMS Livestock, Poultry and Grain Market News | D5: =IFERROR(INDEX('Source Registry'!$I$2:$I$400,MATCH($B5,'Source Registry'!$A$2:$A$400,0))&"","") -> 2 | E5: =IFERROR(INDEX('Source Registry'!$J$2:$J$400,MATCH($B5,'Source Registry'!$A$2:$A$400,0))&"","") -> Daily / weekly | F5: =IFERROR(INDEX('Source Registry'!$U$2:$U$400,MATCH($B5,'Source Registry'!$A$2:$A$400,0))&"","") -> Price and market | G5: =IFERROR(INDEX('Source Registry'!$V$2:$V$400,MATCH($B5,'Source Registry'!$A$2:$A$400,0))&"","") -> Detection feed | H5: =IFERROR(INDEX('Source Registry'!$K$2:$K$400,MATCH($B5,'Source Registry'!$A$2:$A$400,0))&"","") -> Free API (MARS) / web | I5: =IFERROR(INDEX('Source Registry'!$AB$2:$AB$400,MATCH($B5,'Source Registry'!$A$2:$A$400,0))&"","")
A6: =IFERROR(INDEX('Source Registry'!$AA$2:$AA$400,MATCH($B6,'Source Registry'!$A$2:$A$400,0))&"","") -> Wave 1 | B6: S017 | C6: =IFERROR(INDEX('Source Registry'!$B$2:$B$400,MATCH($B6,'Source Registry'!$A$2:$A$400,0))&"","") -> AMS Dairy Market News | D6: =IFERROR(INDEX('Source Registry'!$I$2:$I$400,MATCH($B6,'Source Registry'!$A$2:$A$400,0))&"","") -> 2 | E6: =IFERROR(INDEX('Source Registry'!$J$2:$J$400,MATCH($B6,'Source Registry'!$A$2:$A$400,0))&"","") -> Weekly / daily | F6: =IFERROR(INDEX('Source Registry'!$U$2:$U$400,MATCH($B6,'Source Registry'!$A$2:$A$400,0))&"","") -> Price and market | G6: =IFERROR(INDEX('Source Registry'!$V$2:$V$400,MATCH($B6,'Source Registry'!$A$2:$A$400,0))&"","") -> Detection feed | H6: =IFERROR(INDEX('Source Registry'!$K$2:$K$400,MATCH($B6,'Source Registry'!$A$2:$A$400,0))&"","") -> Free API (MARS) / web | I6: =IFERROR(INDEX('Source Registry'!$AB$2:$AB$400,MATCH($B6,'Source Registry'!$A$2:$A$400,0))&"","")
A7: =IFERROR(INDEX('Source Registry'!$AA$2:$AA$400,MATCH($B7,'Source Registry'!$A$2:$A$400,0))&"","") -> Wave 1 | B7: S057 | C7: =IFERROR(INDEX('Source Registry'!$B$2:$B$400,MATCH($B7,'Source Registry'!$A$2:$A$400,0))&"","") -> Federal Register | D7: =IFERROR(INDEX('Source Registry'!$I$2:$I$400,MATCH($B7,'Source Registry'!$A$2:$A$400,0))&"","") -> 1 | E7: =IFERROR(INDEX('Source Registry'!$J$2:$J$400,MATCH($B7,'Source Registry'!$A$2:$A$400,0))&"","") -> Daily | F7: =IFERROR(INDEX('Source Registry'!$U$2:$U$400,MATCH($B7,'Source Registry'!$A$2:$A$400,0))&"","") -> Policy and regulation | G7: =IFERROR(INDEX('Source Registry'!$V$2:$V$400,MATCH($B7,'Source Registry'!$A$2:$A$400,0))&"","") -> Detection feed | H7: =IFERROR(INDEX('Source Registry'!$K$2:$K$400,MATCH($B7,'Source Registry'!$A$2:$A$400,0))&"","") -> Free API | I7: =IFERROR(INDEX('Source Registry'!$AB$2:$AB$400,MATCH($B7,'Source Registry'!$A$2:$A$400,0))&"","")
A8: =IFERROR(INDEX('Source Registry'!$AA$2:$AA$400,MATCH($B8,'Source Registry'!$A$2:$A$400,0))&"","") -> Wave 1 | B8: S114 | C8: =IFERROR(INDEX('Source Registry'!$B$2:$B$400,MATCH($B8,'Source Registry'!$A$2:$A$400,0))&"","") -> National Weather Service forecasts and alerts | D8: =IFERROR(INDEX('Source Registry'!$I$2:$I$400,MATCH($B8,'Source Registry'!$A$2:$A$400,0))&"","") -> 1 | E8: =IFERROR(INDEX('Source Registry'!$J$2:$J$400,MATCH($B8,'Source Registry'!$A$2:$A$400,0))&"","") -> Continuous | F8: =IFERROR(INDEX('Source Registry'!$U$2:$U$400,MATCH($B8,'Source Registry'!$A$2:$A$400,0))&"","") -> Weather and climate | G8: =IFERROR(INDEX('Source Registry'!$V$2:$V$400,MATCH($B8,'Source Registry'!$A$2:$A$400,0))&"","") -> Detection feed | H8: =IFERROR(INDEX('Source Registry'!$K$2:$K$400,MATCH($B8,'Source Registry'!$A$2:$A$400,0))&"","") -> Free API | I8: =IFERROR(INDEX('Source Registry'!$AB$2:$AB$400,MATCH($B8,'Source Registry'!$A$2:$A$400,0))&"","")
A9: =IFERROR(INDEX('Source Registry'!$AA$2:$AA$400,MATCH($B9,'Source Registry'!$A$2:$A$400,0))&"","") -> Wave 1 | B9: S065 | C9: =IFERROR(INDEX('Source Registry'!$B$2:$B$400,MATCH($B9,'Source Registry'!$A$2:$A$400,0))&"","") -> US Drought Monitor | D9: =IFERROR(INDEX('Source Registry'!$I$2:$I$400,MATCH($B9,'Source Registry'!$A$2:$A$400,0))&"","") -> 1 | E9: =IFERROR(INDEX('Source Registry'!$J$2:$J$400,MATCH($B9,'Source Registry'!$A$2:$A$400,0))&"","") -> Weekly | F9: =IFERROR(INDEX('Source Registry'!$U$2:$U$400,MATCH($B9,'Source Registry'!$A$2:$A$400,0))&"","") -> Weather and climate | G9: =IFERROR(INDEX('Source Registry'!$V$2:$V$400,MATCH($B9,'Source Registry'!$A$2:$A$400,0))&"","") -> Detection feed | H9: =IFERROR(INDEX('Source Registry'!$K$2:$K$400,MATCH($B9,'Source Registry'!$A$2:$A$400,0))&"","") -> Free download / API | I9: =IFERROR(INDEX('Source Registry'!$AB$2:$AB$400,MATCH($B9,'Source Registry'!$A$2:$A$400,0))&"","")
A10: =IFERROR(INDEX('Source Registry'!$AA$2:$AA$400,MATCH($B10,'Source Registry'!$A$2:$A$400,0))&"","") -> Wave 1 | B10: S041 | C10: =IFERROR(INDEX('Source Registry'!$B$2:$B$400,MATCH($B10,'Source Registry'!$A$2:$A$400,0))&"","") -> DTN retail fertilizer trends | D10: =IFERROR(INDEX('Source Registry'!$I$2:$I$400,MATCH($B10,'Source Registry'!$A$2:$A$400,0))&"","") -> 2 | E10: =IFERROR(INDEX('Source Registry'!$J$2:$J$400,MATCH($B10,'Source Registry'!$A$2:$A$400,0))&"","") -> Weekly | F10: =IFERROR(INDEX('Source Registry'!$U$2:$U$400,MATCH($B10,'Source Registry'!$A$2:$A$400,0))&"","") -> Input cost | G10: =IFERROR(INDEX('Source Registry'!$V$2:$V$400,MATCH($B10,'Source Registry'!$A$2:$A$400,0))&"","") -> Detection feed | H10: =IFERROR(INDEX('Source Registry'!$K$2:$K$400,MATCH($B10,'Source Registry'!$A$2:$A$400,0))&"","") -> Free web | I10: =IFERROR(INDEX('Source Registry'!$AB$2:$AB$400,MATCH($B10,'Source Registry'!$A$2:$A$400,0))&"","") -> Web-only; check terms and plan for licensed access or careful scraping
A11: =IFERROR(INDEX('Source Registry'!$AA$2:$AA$400,MATCH($B11,'Source Registry'!$A$2:$A$400,0))&"","") -> Wave 2 | B11: S023 | C11: =IFERROR(INDEX('Source Registry'!$B$2:$B$400,MATCH($B11,'Source Registry'!$A$2:$A$400,0))&"","") -> CME grain and livestock futures | D11: =IFERROR(INDEX('Source Registry'!$I$2:$I$400,MATCH($B11,'Source Registry'!$A$2:$A$400,0))&"","") -> 2 | E11: =IFERROR(INDEX('Source Registry'!$J$2:$J$400,MATCH($B11,'Source Registry'!$A$2:$A$400,0))&"","") -> Daily | F11: =IFERROR(INDEX('Source Registry'!$U$2:$U$400,MATCH($B11,'Source Registry'!$A$2:$A$400,0))&"","") -> Price and market | G11: =IFERROR(INDEX('Source Registry'!$V$2:$V$400,MATCH($B11,'Source Registry'!$A$2:$A$400,0))&"","") -> Detection feed | H11: =IFERROR(INDEX('Source Registry'!$K$2:$K$400,MATCH($B11,'Source Registry'!$A$2:$A$400,0))&"","") -> Delayed free / real-time licensed | I11: =IFERROR(INDEX('Source Registry'!$AB$2:$AB$400,MATCH($B11,'Source Registry'!$A$2:$A$400,0))&"","") -> Confirm CME data licensing for display in a commercial product; fall back to AMS feeds
A12: =IFERROR(INDEX('Source Registry'!$AA$2:$AA$400,MATCH($B12,'Source Registry'!$A$2:$A$400,0))&"","") -> Wave 2 | B12: S022 | C12: =IFERROR(INDEX('Source Registry'!$B$2:$B$400,MATCH($B12,'Source Registry'!$A$2:$A$400,0))&"","") -> CME dairy futures and spot | D12: =IFERROR(INDEX('Source Registry'!$I$2:$I$400,MATCH($B12,'Source Registry'!$A$2:$A$400,0))&"","") -> 2 | E12: =IFERROR(INDEX('Source Registry'!$J$2:$J$400,MATCH($B12,'Source Registry'!$A$2:$A$400,0))&"","") -> Daily | F12: =IFERROR(INDEX('Source Registry'!$U$2:$U$400,MATCH($B12,'Source Registry'!$A$2:$A$400,0))&"","") -> Price and market | G12: =IFERROR(INDEX('Source Registry'!$V$2:$V$400,MATCH($B12,'Source Registry'!$A$2:$A$400,0))&"","") -> Detection feed | H12: =IFERROR(INDEX('Source Registry'!$K$2:$K$400,MATCH($B12,'Source Registry'!$A$2:$A$400,0))&"","") -> Delayed free / real-time licensed | I12: =IFERROR(INDEX('Source Registry'!$AB$2:$AB$400,MATCH($B12,'Source Registry'!$A$2:$A$400,0))&"","") -> Confirm CME data licensing for display in a commercial product; fall back to AMS feeds
A13: =IFERROR(INDEX('Source Registry'!$AA$2:$AA$400,MATCH($B13,'Source Registry'!$A$2:$A$400,0))&"","") -> Wave 2 | B13: S024 | C13: =IFERROR(INDEX('Source Registry'!$B$2:$B$400,MATCH($B13,'Source Registry'!$A$2:$A$400,0))&"","") -> Global Dairy Trade auctions | D13: =IFERROR(INDEX('Source Registry'!$I$2:$I$400,MATCH($B13,'Source Registry'!$A$2:$A$400,0))&"","") -> 2 | E13: =IFERROR(INDEX('Source Registry'!$J$2:$J$400,MATCH($B13,'Source Registry'!$A$2:$A$400,0))&"","") -> Twice monthly | F13: =IFERROR(INDEX('Source Registry'!$U$2:$U$400,MATCH($B13,'Source Registry'!$A$2:$A$400,0))&"","") -> Price and market | G13: =IFERROR(INDEX('Source Registry'!$V$2:$V$400,MATCH($B13,'Source Registry'!$A$2:$A$400,0))&"","") -> Detection feed | H13: =IFERROR(INDEX('Source Registry'!$K$2:$K$400,MATCH($B13,'Source Registry'!$A$2:$A$400,0))&"","") -> Free web | I13: =IFERROR(INDEX('Source Registry'!$AB$2:$AB$400,MATCH($B13,'Source Registry'!$A$2:$A$400,0))&"","") -> Web-only; check terms and plan for licensed access or careful scraping
A14: =IFERROR(INDEX('Source Registry'!$AA$2:$AA$400,MATCH($B14,'Source Registry'!$A$2:$A$400,0))&"","") -> Wave 2 | B14: S153 | C14: =IFERROR(INDEX('Source Registry'!$B$2:$B$400,MATCH($B14,'Source Registry'!$A$2:$A$400,0))&"","") -> AMS hay and feedstuffs reports | D14: =IFERROR(INDEX('Source Registry'!$I$2:$I$400,MATCH($B14,'Source Registry'!$A$2:$A$400,0))&"","") -> 2 | E14: =IFERROR(INDEX('Source Registry'!$J$2:$J$400,MATCH($B14,'Source Registry'!$A$2:$A$400,0))&"","") -> Weekly | F14: =IFERROR(INDEX('Source Registry'!$U$2:$U$400,MATCH($B14,'Source Registry'!$A$2:$A$400,0))&"","") -> Input cost | G14: =IFERROR(INDEX('Source Registry'!$V$2:$V$400,MATCH($B14,'Source Registry'!$A$2:$A$400,0))&"","") -> Detection feed | H14: =IFERROR(INDEX('Source Registry'!$K$2:$K$400,MATCH($B14,'Source Registry'!$A$2:$A$400,0))&"","") -> Free web / API | I14: =IFERROR(INDEX('Source Registry'!$AB$2:$AB$400,MATCH($B14,'Source Registry'!$A$2:$A$400,0))&"","") -> Confirm report names and API access
A15: =IFERROR(INDEX('Source Registry'!$AA$2:$AA$400,MATCH($B15,'Source Registry'!$A$2:$A$400,0))&"","") -> Wave 2 | B15: S072 | C15: =IFERROR(INDEX('Source Registry'!$B$2:$B$400,MATCH($B15,'Source Registry'!$A$2:$A$400,0))&"","") -> Congress.gov | D15: =IFERROR(INDEX('Source Registry'!$I$2:$I$400,MATCH($B15,'Source Registry'!$A$2:$A$400,0))&"","") -> 1 | E15: =IFERROR(INDEX('Source Registry'!$J$2:$J$400,MATCH($B15,'Source Registry'!$A$2:$A$400,0))&"","") -> Daily | F15: =IFERROR(INDEX('Source Registry'!$U$2:$U$400,MATCH($B15,'Source Registry'!$A$2:$A$400,0))&"","") -> Policy and regulation | G15: =IFERROR(INDEX('Source Registry'!$V$2:$V$400,MATCH($B15,'Source Registry'!$A$2:$A$400,0))&"","") -> Detection feed | H15: =IFERROR(INDEX('Source Registry'!$K$2:$K$400,MATCH($B15,'Source Registry'!$A$2:$A$400,0))&"","") -> Free web / API | I15: =IFERROR(INDEX('Source Registry'!$AB$2:$AB$400,MATCH($B15,'Source Registry'!$A$2:$A$400,0))&"","")
A16: =IFERROR(INDEX('Source Registry'!$AA$2:$AA$400,MATCH($B16,'Source Registry'!$A$2:$A$400,0))&"","") -> Wave 2 | B16: S093 | C16: =IFERROR(INDEX('Source Registry'!$B$2:$B$400,MATCH($B16,'Source Registry'!$A$2:$A$400,0))&"","") -> LegiScan | D16: =IFERROR(INDEX('Source Registry'!$I$2:$I$400,MATCH($B16,'Source Registry'!$A$2:$A$400,0))&"","") -> 2 | E16: =IFERROR(INDEX('Source Registry'!$J$2:$J$400,MATCH($B16,'Source Registry'!$A$2:$A$400,0))&"","") -> Daily | F16: =IFERROR(INDEX('Source Registry'!$U$2:$U$400,MATCH($B16,'Source Registry'!$A$2:$A$400,0))&"","") -> Policy and regulation | G16: =IFERROR(INDEX('Source Registry'!$V$2:$V$400,MATCH($B16,'Source Registry'!$A$2:$A$400,0))&"","") -> Detection feed | H16: =IFERROR(INDEX('Source Registry'!$K$2:$K$400,MATCH($B16,'Source Registry'!$A$2:$A$400,0))&"","") -> Free tier / paid API | I16: =IFERROR(INDEX('Source Registry'!$AB$2:$AB$400,MATCH($B16,'Source Registry'!$A$2:$A$400,0))&"","") -> Free tier has limits
... A19: =IFERROR(INDEX('Source Registry'!$AA$2:$AA$400,MATCH($B19,'Source Registry'!$A$2:$A$400,0))&"","") -> Wave 3 | B19: S040 | C19: =IFERROR(INDEX('Source Registry'!$B$2:$B$400,MATCH($B19,'Source Registry'!$A$2:$A$400,0))&"","") -> APHIS animal health data | D19: =IFERROR(INDEX('Source Registry'!$I$2:$I$400,MATCH($B19,'Source Registry'!$A$2:$A$400,0))&"","") -> 1 | E19: =IFERROR(INDEX('Source Registry'!$J$2:$J$400,MATCH($B19,'Source Registry'!$A$2:$A$400,0))&"","") -> Event-driven | F19: =IFERROR(INDEX('Source Registry'!$U$2:$U$400,MATCH($B19,'Source Registry'!$A$2:$A$400,0))&"","") -> Disease and border | G19: =IFERROR(INDEX('Source Registry'!$V$2:$V$400,MATCH($B19,'Source Registry'!$A$2:$A$400,0))&"","") -> Detection feed | H19: =IFERROR(INDEX('Source Registry'!$K$2:$K$400,MATCH($B19,'Source Registry'!$A$2:$A$400,0))&"","") -> Free web | I19: =IFERROR(INDEX('Source Registry'!$AB$2:$AB$400,MATCH($B19,'Source Registry'!$A$2:$A$400,0))&"","") -> Web notices with no clear API; check terms
A22: Summary
A23: Sources in the MVP | C23: =COUNTA($B$5:$B$19) -> 15
A24: Authority tier 2 | C24: =COUNTIF($D$5:$D$19,"2") -> 9
A25: Authority tier 1 | C25: =COUNTIF($D$5:$D$19,"1") -> 6
A26: Wave 1 | C26: =COUNTIF($A$5:$A$19,"Wave 1") -> 6
A27: Wave 2 | C27: =COUNTIF($A$5:$A$19,"Wave 2") -> 6
A28: Wave 3 | C28: =COUNTIF($A$5:$A$19,"Wave 3") -> 3
A29: Trigger families covered | C29: =SUMPRODUCT(1/COUNTIF($F$5:$F$19,$F$5:$F$19)) -> 6
A31: Not in the MVP, first to add next: WASDE (verification baseline), eggs and specialty crops (if a pilot farm needs them), credit sources, and Regulations.gov for comment dockets.

Sheet Driver Coverage
A1: Driver coverage: how many registered sources back each driver
A2: All counts are formulas over the Source Registry. Add or change rows there and these update.
A4: Driver | B4: Total sources | C4: Authority 1 (official) | D4: Authority 2 (market / trade) | E4: Authority 3 (analyst) | F4: Near-term | G4: Long-term | H4: Both horizons | I4: Connected or live | J4: % connected or live
A5: Global Affluence | B5: =COUNTIF('Source Registry'!$F$2:$F$300,$A5) -> 14 | C5: =COUNTIFS('Source Registry'!$F$2:$F$300,$A5,'Source Registry'!$I$2:$I$300,1) -> 7 | D5: =COUNTIFS('Source Registry'!$F$2:$F$300,$A5,'Source Registry'!$I$2:$I$300,2) -> 5 | E5: =COUNTIFS('Source Registry'!$F$2:$F$300,$A5,'Source Registry'!$I$2:$I$300,3) -> 2 | F5: =COUNTIFS('Source Registry'!$F$2:$F$300,$A5,'Source Registry'!$G$2:$G$300,"Near-term (1-2 seasons)") -> 1 | G5: =COUNTIFS('Source Registry'!$F$2:$F$300,$A5,'Source Registry'!$G$2:$G$300,"Long-term (3-10 yrs)") -> 7 | H5: =COUNTIFS('Source Registry'!$F$2:$F$300,$A5,'Source Registry'!$G$2:$G$300,"Both") -> 6 | I5: =COUNTIFS('Source Registry'!$F$2:$F$300,$A5,'Source Registry'!$T$2:$T$300,"Connected")+COUNTIFS('Source Registry'!$F$2:$F$300,$A5,'Source Registry'!$T$2:$T$300,"Live in agent") -> 0 | J5: =IF(B5=0,0,I5/B5) -> 0
A6: Geopolitics | B6: =COUNTIF('Source Registry'!$F$2:$F$300,$A6) -> 19 | C6: =COUNTIFS('Source Registry'!$F$2:$F$300,$A6,'Source Registry'!$I$2:$I$300,1) -> 15 | D6: =COUNTIFS('Source Registry'!$F$2:$F$300,$A6,'Source Registry'!$I$2:$I$300,2) -> 4 | E6: =COUNTIFS('Source Registry'!$F$2:$F$300,$A6,'Source Registry'!$I$2:$I$300,3) -> 0 | F6: =COUNTIFS('Source Registry'!$F$2:$F$300,$A6,'Source Registry'!$G$2:$G$300,"Near-term (1-2 seasons)") -> 6 | G6: =COUNTIFS('Source Registry'!$F$2:$F$300,$A6,'Source Registry'!$G$2:$G$300,"Long-term (3-10 yrs)") -> 3 | H6: =COUNTIFS('Source Registry'!$F$2:$F$300,$A6,'Source Registry'!$G$2:$G$300,"Both") -> 10 | I6: =COUNTIFS('Source Registry'!$F$2:$F$300,$A6,'Source Registry'!$T$2:$T$300,"Connected")+COUNTIFS('Source Registry'!$F$2:$F$300,$A6,'Source Registry'!$T$2:$T$300,"Live in agent") -> 0 | J6: =IF(B6=0,0,I6/B6) -> 0
A7: Human Health | B7: =COUNTIF('Source Registry'!$F$2:$F$300,$A7) -> 16 | C7: =COUNTIFS('Source Registry'!$F$2:$F$300,$A7,'Source Registry'!$I$2:$I$300,1) -> 8 | D7: =COUNTIFS('Source Registry'!$F$2:$F$300,$A7,'Source Registry'!$I$2:$I$300,2) -> 6 | E7: =COUNTIFS('Source Registry'!$F$2:$F$300,$A7,'Source Registry'!$I$2:$I$300,3) -> 2 | F7: =COUNTIFS('Source Registry'!$F$2:$F$300,$A7,'Source Registry'!$G$2:$G$300,"Near-term (1-2 seasons)") -> 3 | G7: =COUNTIFS('Source Registry'!$F$2:$F$300,$A7,'Source Registry'!$G$2:$G$300,"Long-term (3-10 yrs)") -> 5 | H7: =COUNTIFS('Source Registry'!$F$2:$F$300,$A7,'Source Registry'!$G$2:$G$300,"Both") -> 8 | I7: =COUNTIFS('Source Registry'!$F$2:$F$300,$A7,'Source Registry'!$T$2:$T$300,"Connected")+COUNTIFS('Source Registry'!$F$2:$F$300,$A7,'Source Registry'!$T$2:$T$300,"Live in agent") -> 0 | J7: =IF(B7=0,0,I7/B7) -> 0
A8: Climate Volatility | B8: =COUNTIF('Source Registry'!$F$2:$F$300,$A8) -> 32 | C8: =COUNTIFS('Source Registry'!$F$2:$F$300,$A8,'Source Registry'!$I$2:$I$300,1) -> 25 | D8: =COUNTIFS('Source Registry'!$F$2:$F$300,$A8,'Source Registry'!$I$2:$I$300,2) -> 7 | E8: =COUNTIFS('Source Registry'!$F$2:$F$300,$A8,'Source Registry'!$I$2:$I$300,3) -> 0 | F8: =COUNTIFS('Source Registry'!$F$2:$F$300,$A8,'Source Registry'!$G$2:$G$300,"Near-term (1-2 seasons)") -> 19 | G8: =COUNTIFS('Source Registry'!$F$2:$F$300,$A8,'Source Registry'!$G$2:$G$300,"Long-term (3-10 yrs)") -> 7 | H8: =COUNTIFS('Source Registry'!$F$2:$F$300,$A8,'Source Registry'!$G$2:$G$300,"Both") -> 6 | I8: =COUNTIFS('Source Registry'!$F$2:$F$300,$A8,'Source Registry'!$T$2:$T$300,"Connected")+COUNTIFS('Source Registry'!$F$2:$F$300,$A8,'Source Registry'!$T$2:$T$300,"Live in agent") -> 0 | J8: =IF(B8=0,0,I8/B8) -> 0
A9: Technology | B9: =COUNTIF('Source Registry'!$F$2:$F$300,$A9) -> 11 | C9: =COUNTIFS('Source Registry'!$F$2:$F$300,$A9,'Source Registry'!$I$2:$I$300,1) -> 6 | D9: =COUNTIFS('Source Registry'!$F$2:$F$300,$A9,'Source Registry'!$I$2:$I$300,2) -> 3 | E9: =COUNTIFS('Source Registry'!$F$2:$F$300,$A9,'Source Registry'!$I$2:$I$300,3) -> 2 | F9: =COUNTIFS('Source Registry'!$F$2:$F$300,$A9,'Source Registry'!$G$2:$G$300,"Near-term (1-2 seasons)") -> 2 | G9: =COUNTIFS('Source Registry'!$F$2:$F$300,$A9,'Source Registry'!$G$2:$G$300,"Long-term (3-10 yrs)") -> 4 | H9: =COUNTIFS('Source Registry'!$F$2:$F$300,$A9,'Source Registry'!$G$2:$G$300,"Both") -> 5 | I9: =COUNTIFS('Source Registry'!$F$2:$F$300,$A9,'Source Registry'!$T$2:$T$300,"Connected")+COUNTIFS('Source Registry'!$F$2:$F$300,$A9,'Source Registry'!$T$2:$T$300,"Live in agent") -> 0 | J9: =IF(B9=0,0,I9/B9) -> 0
A10: Ownership | B10: =COUNTIF('Source Registry'!$F$2:$F$300,$A10) -> 16 | C10: =COUNTIFS('Source Registry'!$F$2:$F$300,$A10,'Source Registry'!$I$2:$I$300,1) -> 9 | D10: =COUNTIFS('Source Registry'!$F$2:$F$300,$A10,'Source Registry'!$I$2:$I$300,2) -> 4 | E10: =COUNTIFS('Source Registry'!$F$2:$F$300,$A10,'Source Registry'!$I$2:$I$300,3) -> 3 | F10: =COUNTIFS('Source Registry'!$F$2:$F$300,$A10,'Source Registry'!$G$2:$G$300,"Near-term (1-2 seasons)") -> 6 | G10: =COUNTIFS('Source Registry'!$F$2:$F$300,$A10,'Source Registry'!$G$2:$G$300,"Long-term (3-10 yrs)") -> 5 | H10: =COUNTIFS('Source Registry'!$F$2:$F$300,$A10,'Source Registry'!$G$2:$G$300,"Both") -> 5 | I10: =COUNTIFS('Source Registry'!$F$2:$F$300,$A10,'Source Registry'!$T$2:$T$300,"Connected")+COUNTIFS('Source Registry'!$F$2:$F$300,$A10,'Source Registry'!$T$2:$T$300,"Live in agent") -> 0 | J10: =IF(B10=0,0,I10/B10) -> 0
A11: Cross-driver | B11: =COUNTIF('Source Registry'!$F$2:$F$300,$A11) -> 44 | C11: =COUNTIFS('Source Registry'!$F$2:$F$300,$A11,'Source Registry'!$I$2:$I$300,1) -> 23 | D11: =COUNTIFS('Source Registry'!$F$2:$F$300,$A11,'Source Registry'!$I$2:$I$300,2) -> 8 | E11: =COUNTIFS('Source Registry'!$F$2:$F$300,$A11,'Source Registry'!$I$2:$I$300,3) -> 13 | F11: =COUNTIFS('Source Registry'!$F$2:$F$300,$A11,'Source Registry'!$G$2:$G$300,"Near-term (1-2 seasons)") -> 0 | G11: =COUNTIFS('Source Registry'!$F$2:$F$300,$A11,'Source Registry'!$G$2:$G$300,"Long-term (3-10 yrs)") -> 3 | H11: =COUNTIFS('Source Registry'!$F$2:$F$300,$A11,'Source Registry'!$G$2:$G$300,"Both") -> 41 | I11: =COUNTIFS('Source Registry'!$F$2:$F$300,$A11,'Source Registry'!$T$2:$T$300,"Connected")+COUNTIFS('Source Registry'!$F$2:$F$300,$A11,'Source Registry'!$T$2:$T$300,"Live in agent") -> 0 | J11: =IF(B11=0,0,I11/B11) -> 0
A12: Core S&D (baseline) | B12: =COUNTIF('Source Registry'!$F$2:$F$300,$A12) -> 36 | C12: =COUNTIFS('Source Registry'!$F$2:$F$300,$A12,'Source Registry'!$I$2:$I$300,1) -> 19 | D12: =COUNTIFS('Source Registry'!$F$2:$F$300,$A12,'Source Registry'!$I$2:$I$300,2) -> 13 | E12: =COUNTIFS('Source Registry'!$F$2:$F$300,$A12,'Source Registry'!$I$2:$I$300,3) -> 4 | F12: =COUNTIFS('Source Registry'!$F$2:$F$300,$A12,'Source Registry'!$G$2:$G$300,"Near-term (1-2 seasons)") -> 29 | G12: =COUNTIFS('Source Registry'!$F$2:$F$300,$A12,'Source Registry'!$G$2:$G$300,"Long-term (3-10 yrs)") -> 2 | H12: =COUNTIFS('Source Registry'!$F$2:$F$300,$A12,'Source Registry'!$G$2:$G$300,"Both") -> 5 | I12: =COUNTIFS('Source Registry'!$F$2:$F$300,$A12,'Source Registry'!$T$2:$T$300,"Connected")+COUNTIFS('Source Registry'!$F$2:$F$300,$A12,'Source Registry'!$T$2:$T$300,"Live in agent") -> 0 | J12: =IF(B12=0,0,I12/B12) -> 0
A13: Total | B13: =SUM(B5:B12) -> 188 | C13: =SUM(C5:C12) -> 112 | D13: =SUM(D5:D12) -> 50 | E13: =SUM(E5:E12) -> 26 | F13: =SUM(F5:F12) -> 66 | G13: =SUM(G5:G12) -> 36 | H13: =SUM(H5:H12) -> 86 | I13: =SUM(I5:I12) -> 0 | J13: =IF(B13=0,0,I13/B13) -> 0
A14: Check: total should equal the number of registry rows | B14: =COUNTA('Source Registry'!$A$2:$A$300) -> 188 | C14: =IF(B13=B14,"OK","Check driver labels") -> OK
A16: Coverage by commodity group
A17: Commodity group | B17: Total sources | C17: Authority 1 | D17: Authority 2 | E17: Authority 3 | F17: Price & market sources | G17: Trade flow sources | H17: Analyst sources | I17: Policy sources
A18: Cross-commodity | B18: =COUNTIF('Source Registry'!$D$2:$D$300,$A18) -> 120 | C18: =COUNTIFS('Source Registry'!$D$2:$D$300,$A18,'Source Registry'!$I$2:$I$300,1) -> 78 | D18: =COUNTIFS('Source Registry'!$D$2:$D$300,$A18,'Source Registry'!$I$2:$I$300,2) -> 32 | E18: =COUNTIFS('Source Registry'!$D$2:$D$300,$A18,'Source Registry'!$I$2:$I$300,3) -> 10 | F18: =COUNTIFS('Source Registry'!$D$2:$D$300,$A18,'Source Registry'!$E$2:$E$300,"Price & market") -> 1 | G18: =COUNTIFS('Source Registry'!$D$2:$D$300,$A18,'Source Registry'!$E$2:$E$300,"Trade flow") -> 5 | H18: =COUNTIFS('Source Registry'!$D$2:$D$300,$A18,'Source Registry'!$E$2:$E$300,"Analyst") -> 4 | I18: =COUNTIFS('Source Registry'!$D$2:$D$300,$A18,'Source Registry'!$E$2:$E$300,"Policy") -> 34
A19: Dairy | B19: =COUNTIF('Source Registry'!$D$2:$D$300,$A19) -> 12 | C19: =COUNTIFS('Source Registry'!$D$2:$D$300,$A19,'Source Registry'!$I$2:$I$300,1) -> 6 | D19: =COUNTIFS('Source Registry'!$D$2:$D$300,$A19,'Source Registry'!$I$2:$I$300,2) -> 4 | E19: =COUNTIFS('Source Registry'!$D$2:$D$300,$A19,'Source Registry'!$I$2:$I$300,3) -> 2 | F19: =COUNTIFS('Source Registry'!$D$2:$D$300,$A19,'Source Registry'!$E$2:$E$300,"Price & market") -> 4 | G19: =COUNTIFS('Source Registry'!$D$2:$D$300,$A19,'Source Registry'!$E$2:$E$300,"Trade flow") -> 1 | H19: =COUNTIFS('Source Registry'!$D$2:$D$300,$A19,'Source Registry'!$E$2:$E$300,"Analyst") -> 1 | I19: =COUNTIFS('Source Registry'!$D$2:$D$300,$A19,'Source Registry'!$E$2:$E$300,"Policy") -> 2
A20: Grains & oilseeds | B20: =COUNTIF('Source Registry'!$D$2:$D$300,$A20) -> 14 | C20: =COUNTIFS('Source Registry'!$D$2:$D$300,$A20,'Source Registry'!$I$2:$I$300,1) -> 7 | D20: =COUNTIFS('Source Registry'!$D$2:$D$300,$A20,'Source Registry'!$I$2:$I$300,2) -> 4 | E20: =COUNTIFS('Source Registry'!$D$2:$D$300,$A20,'Source Registry'!$I$2:$I$300,3) -> 3 | F20: =COUNTIFS('Source Registry'!$D$2:$D$300,$A20,'Source Registry'!$E$2:$E$300,"Price & market") -> 1 | G20: =COUNTIFS('Source Registry'!$D$2:$D$300,$A20,'Source Registry'!$E$2:$E$300,"Trade flow") -> 1 | H20: =COUNTIFS('Source Registry'!$D$2:$D$300,$A20,'Source Registry'!$E$2:$E$300,"Analyst") -> 0 | I20: =COUNTIFS('Source Registry'!$D$2:$D$300,$A20,'Source Registry'!$E$2:$E$300,"Policy") -> 4
A21: Livestock & poultry | B21: =COUNTIF('Source Registry'!$D$2:$D$300,$A21) -> 15 | C21: =COUNTIFS('Source Registry'!$D$2:$D$300,$A21,'Source Registry'!$I$2:$I$300,1) -> 6 | D21: =COUNTIFS('Source Registry'!$D$2:$D$300,$A21,'Source Registry'!$I$2:$I$300,2) -> 3 | E21: =COUNTIFS('Source Registry'!$D$2:$D$300,$A21,'Source Registry'!$I$2:$I$300,3) -> 6 | F21: =COUNTIFS('Source Registry'!$D$2:$D$300,$A21,'Source Registry'!$E$2:$E$300,"Price & market") -> 2 | G21: =COUNTIFS('Source Registry'!$D$2:$D$300,$A21,'Source Registry'!$E$2:$E$300,"Trade flow") -> 0 | H21: =COUNTIFS('Source Registry'!$D$2:$D$300,$A21,'Source Registry'!$E$2:$E$300,"Analyst") -> 2 | I21: =COUNTIFS('Source Registry'!$D$2:$D$300,$A21,'Source Registry'!$E$2:$E$300,"Policy") -> 8
A22: Specialty crops | B22: =COUNTIF('Source Registry'!$D$2:$D$300,$A22) -> 5 | C22: =COUNTIFS('Source Registry'!$D$2:$D$300,$A22,'Source Registry'!$I$2:$I$300,1) -> 3 | D22: =COUNTIFS('Source Registry'!$D$2:$D$300,$A22,'Source Registry'!$I$2:$I$300,2) -> 1 | E22: =COUNTIFS('Source Registry'!$D$2:$D$300,$A22,'Source Registry'!$I$2:$I$300,3) -> 1 | F22: =COUNTIFS('Source Registry'!$D$2:$D$300,$A22,'Source Registry'!$E$2:$E$300,"Price & market") -> 1 | G22: =COUNTIFS('Source Registry'!$D$2:$D$300,$A22,'Source Registry'!$E$2:$E$300,"Trade flow") -> 0 | H22: =COUNTIFS('Source Registry'!$D$2:$D$300,$A22,'Source Registry'!$E$2:$E$300,"Analyst") -> 0 | I22: =COUNTIFS('Source Registry'!$D$2:$D$300,$A22,'Source Registry'!$E$2:$E$300,"Policy") -> 3
A23: Inputs | B23: =COUNTIF('Source Registry'!$D$2:$D$300,$A23) -> 6 | C23: =COUNTIFS('Source Registry'!$D$2:$D$300,$A23,'Source Registry'!$I$2:$I$300,1) -> 2 | D23: =COUNTIFS('Source Registry'!$D$2:$D$300,$A23,'Source Registry'!$I$2:$I$300,2) -> 3 | E23: =COUNTIFS('Source Registry'!$D$2:$D$300,$A23,'Source Registry'!$I$2:$I$300,3) -> 1 | F23: =COUNTIFS('Source Registry'!$D$2:$D$300,$A23,'Source Registry'!$E$2:$E$300,"Price & market") -> 3 | G23: =COUNTIFS('Source Registry'!$D$2:$D$300,$A23,'Source Registry'!$E$2:$E$300,"Trade flow") -> 0 | H23: =COUNTIFS('Source Registry'!$D$2:$D$300,$A23,'Source Registry'!$E$2:$E$300,"Analyst") -> 0 | I23: =COUNTIFS('Source Registry'!$D$2:$D$300,$A23,'Source Registry'!$E$2:$E$300,"Policy") -> 2
A24: Farm economy | B24: =COUNTIF('Source Registry'!$D$2:$D$300,$A24) -> 10 | C24: =COUNTIFS('Source Registry'!$D$2:$D$300,$A24,'Source Registry'!$I$2:$I$300,1) -> 7 | D24: =COUNTIFS('Source Registry'!$D$2:$D$300,$A24,'Source Registry'!$I$2:$I$300,2) -> 1 | E24: =COUNTIFS('Source Registry'!$D$2:$D$300,$A24,'Source Registry'!$I$2:$I$300,3) -> 2 | F24: =COUNTIFS('Source Registry'!$D$2:$D$300,$A24,'Source Registry'!$E$2:$E$300,"Price & market") -> 0 | G24: =COUNTIFS('Source Registry'!$D$2:$D$300,$A24,'Source Registry'!$E$2:$E$300,"Trade flow") -> 0 | H24: =COUNTIFS('Source Registry'!$D$2:$D$300,$A24,'Source Registry'!$E$2:$E$300,"Analyst") -> 2 | I24: =COUNTIFS('Source Registry'!$D$2:$D$300,$A24,'Source Registry'!$E$2:$E$300,"Policy") -> 1
A25: Ownership | B25: =COUNTIF('Source Registry'!$D$2:$D$300,$A25) -> 6 | C25: =COUNTIFS('Source Registry'!$D$2:$D$300,$A25,'Source Registry'!$I$2:$I$300,1) -> 3 | D25: =COUNTIFS('Source Registry'!$D$2:$D$300,$A25,'Source Registry'!$I$2:$I$300,2) -> 2 | E25: =COUNTIFS('Source Registry'!$D$2:$D$300,$A25,'Source Registry'!$I$2:$I$300,3) -> 1 | F25: =COUNTIFS('Source Registry'!$D$2:$D$300,$A25,'Source Registry'!$E$2:$E$300,"Price & market") -> 0 | G25: =COUNTIFS('Source Registry'!$D$2:$D$300,$A25,'Source Registry'!$E$2:$E$300,"Trade flow") -> 0 | H25: =COUNTIFS('Source Registry'!$D$2:$D$300,$A25,'Source Registry'!$E$2:$E$300,"Analyst") -> 1 | I25: =COUNTIFS('Source Registry'!$D$2:$D$300,$A25,'Source Registry'!$E$2:$E$300,"Policy") -> 0
A27: Note: Cross-commodity sources (WASDE, PSD, GATS) cover every group, so a group with few direct rows is not necessarily thin; check its commodity-specific price and trade sources.
A29: Independence: how many sources are real, separate signals
A30: Origin | B30: Sources | C30: Independent: Yes | D30: Partial | E30: No
A31: Original measurement | B31: =COUNTIF('Source Registry'!$O$2:$O$300,$A31) -> 99 | C31: =COUNTIFS('Source Registry'!$O$2:$O$300,$A31,'Source Registry'!$R$2:$R$300,"Yes") -> 98 | D31: =COUNTIFS('Source Registry'!$O$2:$O$300,$A31,'Source Registry'!$R$2:$R$300,"Partial") -> 1 | E31: =COUNTIFS('Source Registry'!$O$2:$O$300,$A31,'Source Registry'!$R$2:$R$300,"No") -> 0
A32: Market-generated | B32: =COUNTIF('Source Registry'!$O$2:$O$300,$A32) -> 10 | C32: =COUNTIFS('Source Registry'!$O$2:$O$300,$A32,'Source Registry'!$R$2:$R$300,"Yes") -> 8 | D32: =COUNTIFS('Source Registry'!$O$2:$O$300,$A32,'Source Registry'!$R$2:$R$300,"Partial") -> 2 | E32: =COUNTIFS('Source Registry'!$O$2:$O$300,$A32,'Source Registry'!$R$2:$R$300,"No") -> 0
A33: Derived | B33: =COUNTIF('Source Registry'!$O$2:$O$300,$A33) -> 35 | C33: =COUNTIFS('Source Registry'!$O$2:$O$300,$A33,'Source Registry'!$R$2:$R$300,"Yes") -> 1 | D33: =COUNTIFS('Source Registry'!$O$2:$O$300,$A33,'Source Registry'!$R$2:$R$300,"Partial") -> 18 | E33: =COUNTIFS('Source Registry'!$O$2:$O$300,$A33,'Source Registry'!$R$2:$R$300,"No") -> 16
A34: Mixed | B34: =COUNTIF('Source Registry'!$O$2:$O$300,$A34) -> 33 | C34: =COUNTIFS('Source Registry'!$O$2:$O$300,$A34,'Source Registry'!$R$2:$R$300,"Yes") -> 3 | D34: =COUNTIFS('Source Registry'!$O$2:$O$300,$A34,'Source Registry'!$R$2:$R$300,"Partial") -> 29 | E34: =COUNTIFS('Source Registry'!$O$2:$O$300,$A34,'Source Registry'!$R$2:$R$300,"No") -> 1
A35: Opinion | B35: =COUNTIF('Source Registry'!$O$2:$O$300,$A35) -> 11 | C35: =COUNTIFS('Source Registry'!$O$2:$O$300,$A35,'Source Registry'!$R$2:$R$300,"Yes") -> 0 | D35: =COUNTIFS('Source Registry'!$O$2:$O$300,$A35,'Source Registry'!$R$2:$R$300,"Partial") -> 0 | E35: =COUNTIFS('Source Registry'!$O$2:$O$300,$A35,'Source Registry'!$R$2:$R$300,"No") -> 11
A37: Registered sources | B37: =COUNTA('Source Registry'!$A$2:$A$300) -> 188
A38: Distinct root sources | B38: =SUMPRODUCT(('Source Registry'!$Q$2:$Q$300<>"")/(COUNTIF('Source Registry'!$Q$2:$Q$300,'Source Registry'!$Q$2:$Q$300)+('Source Registry'!$Q$2:$Q$300=""))) -> 161
A39: Sources that echo another (Independent = No) | B39: =COUNTIF('Source Registry'!$R$2:$R$300,"No") -> 28
A40: Share of sources that are separate roots | B40: =IF(B37=0,0,B38/B37) -> 0.85638298

Sheet Root Check
A1: Root check: are these sources really independent?
A2: Type up to five source IDs from the registry that support one claim (yellow cells). The sheet shows each source's root and whether it builds on the others. The three IDs shown are an example of an echo; replace them.
A4: Slot | B4: Source ID | C4: Source | D4: Origin | E4: Root ID | F4: Root source | G4: Independent signal | H4: Depends on | I4: Builds on another selected source
A5: 1 | B5: S007 | C5: =IF(B5="","",IFERROR(INDEX('Source Registry'!$B$2:$B$300,MATCH(B5,'Source Registry'!$A$2:$A$300,0)),"ID not found")) -> ERS Dairy and Livestock Outlooks | D5: =IF(B5="","",IFERROR(INDEX('Source Registry'!$O$2:$O$300,MATCH(B5,'Source Registry'!$A$2:$A$300,0))&"","")) -> Derived | E5: =IF(B5="","",IFERROR(INDEX('Source Registry'!$Q$2:$Q$300,MATCH(B5,'Source Registry'!$A$2:$A$300,0))&"","")) -> S001 | F5: =IF(E5="","",IFERROR(INDEX('Source Registry'!$B$2:$B$300,MATCH(E5,'Source Registry'!$A$2:$A$300,0)),"")) -> WASDE | G5: =IF(B5="","",IFERROR(INDEX('Source Registry'!$R$2:$R$300,MATCH(B5,'Source Registry'!$A$2:$A$300,0))&"","")) -> No | H5: =IF(B5="","",IFERROR(INDEX('Source Registry'!$P$2:$P$300,MATCH(B5,'Source Registry'!$A$2:$A$300,0))&"","")) -> S001, S006, S017, S005 | I5: =IF(B5="","",SUMPRODUCT(($B$5:$B$9<>"")*($B$5:$B$9<>B5)*ISNUMBER(SEARCH($B$5:$B$9,H5)))) -> 1
A6: 2 | B6: S001 | C6: =IF(B6="","",IFERROR(INDEX('Source Registry'!$B$2:$B$300,MATCH(B6,'Source Registry'!$A$2:$A$300,0)),"ID not found")) -> WASDE | D6: =IF(B6="","",IFERROR(INDEX('Source Registry'!$O$2:$O$300,MATCH(B6,'Source Registry'!$A$2:$A$300,0))&"","")) -> Mixed | E6: =IF(B6="","",IFERROR(INDEX('Source Registry'!$Q$2:$Q$300,MATCH(B6,'Source Registry'!$A$2:$A$300,0))&"","")) -> S001 | F6: =IF(E6="","",IFERROR(INDEX('Source Registry'!$B$2:$B$300,MATCH(E6,'Source Registry'!$A$2:$A$300,0)),"")) -> WASDE | G6: =IF(B6="","",IFERROR(INDEX('Source Registry'!$R$2:$R$300,MATCH(B6,'Source Registry'!$A$2:$A$300,0))&"","")) -> Partial | H6: =IF(B6="","",IFERROR(INDEX('Source Registry'!$P$2:$P$300,MATCH(B6,'Source Registry'!$A$2:$A$300,0))&"","")) -> S003, S025, S026, S027 | I6: =IF(B6="","",SUMPRODUCT(($B$5:$B$9<>"")*($B$5:$B$9<>B6)*ISNUMBER(SEARCH($B$5:$B$9,H6)))) -> 0
A7: 3 | B7: S043 | C7: =IF(B7="","",IFERROR(INDEX('Source Registry'!$B$2:$B$300,MATCH(B7,'Source Registry'!$A$2:$A$300,0)),"ID not found")) -> farmdoc daily | D7: =IF(B7="","",IFERROR(INDEX('Source Registry'!$O$2:$O$300,MATCH(B7,'Source Registry'!$A$2:$A$300,0))&"","")) -> Derived | E7: =IF(B7="","",IFERROR(INDEX('Source Registry'!$Q$2:$Q$300,MATCH(B7,'Source Registry'!$A$2:$A$300,0))&"","")) -> S001 | F7: =IF(E7="","",IFERROR(INDEX('Source Registry'!$B$2:$B$300,MATCH(E7,'Source Registry'!$A$2:$A$300,0)),"")) -> WASDE | G7: =IF(B7="","",IFERROR(INDEX('Source Registry'!$R$2:$R$300,MATCH(B7,'Source Registry'!$A$2:$A$300,0))&"","")) -> No | H7: =IF(B7="","",IFERROR(INDEX('Source Registry'!$P$2:$P$300,MATCH(B7,'Source Registry'!$A$2:$A$300,0))&"","")) -> S001, S003, S022, S023 | I7: =IF(B7="","",SUMPRODUCT(($B$5:$B$9<>"")*($B$5:$B$9<>B7)*ISNUMBER(SEARCH($B$5:$B$9,H7)))) -> 1
A8: 4 | C8: =IF(B8="","",IFERROR(INDEX('Source Registry'!$B$2:$B$300,MATCH(B8,'Source Registry'!$A$2:$A$300,0)),"ID not found")) | D8: =IF(B8="","",IFERROR(INDEX('Source Registry'!$O$2:$O$300,MATCH(B8,'Source Registry'!$A$2:$A$300,0))&"","")) | E8: =IF(B8="","",IFERROR(INDEX('Source Registry'!$Q$2:$Q$300,MATCH(B8,'Source Registry'!$A$2:$A$300,0))&"","")) | F8: =IF(E8="","",IFERROR(INDEX('Source Registry'!$B$2:$B$300,MATCH(E8,'Source Registry'!$A$2:$A$300,0)),"")) | G8: =IF(B8="","",IFERROR(INDEX('Source Registry'!$R$2:$R$300,MATCH(B8,'Source Registry'!$A$2:$A$300,0))&"","")) | H8: =IF(B8="","",IFERROR(INDEX('Source Registry'!$P$2:$P$300,MATCH(B8,'Source Registry'!$A$2:$A$300,0))&"","")) | I8: =IF(B8="","",SUMPRODUCT(($B$5:$B$9<>"")*($B$5:$B$9<>B8)*ISNUMBER(SEARCH($B$5:$B$9,H8))))
A9: 5 | C9: =IF(B9="","",IFERROR(INDEX('Source Registry'!$B$2:$B$300,MATCH(B9,'Source Registry'!$A$2:$A$300,0)),"ID not found")) | D9: =IF(B9="","",IFERROR(INDEX('Source Registry'!$O$2:$O$300,MATCH(B9,'Source Registry'!$A$2:$A$300,0))&"","")) | E9: =IF(B9="","",IFERROR(INDEX('Source Registry'!$Q$2:$Q$300,MATCH(B9,'Source Registry'!$A$2:$A$300,0))&"","")) | F9: =IF(E9="","",IFERROR(INDEX('Source Registry'!$B$2:$B$300,MATCH(E9,'Source Registry'!$A$2:$A$300,0)),"")) | G9: =IF(B9="","",IFERROR(INDEX('Source Registry'!$R$2:$R$300,MATCH(B9,'Source Registry'!$A$2:$A$300,0))&"","")) | H9: =IF(B9="","",IFERROR(INDEX('Source Registry'!$P$2:$P$300,MATCH(B9,'Source Registry'!$A$2:$A$300,0))&"","")) | I9: =IF(B9="","",SUMPRODUCT(($B$5:$B$9<>"")*($B$5:$B$9<>B9)*ISNUMBER(SEARCH($B$5:$B$9,H9))))
A11: Sources selected | C11: =COUNTIF(B5:B9,"?*") -> 3
A12: Independent roots | C12: =SUMPRODUCT((E5:E9<>"")/(COUNTIF(E5:E9,E5:E9)+(E5:E9=""))) -> 1
A13: Sources building on another selected | C13: =COUNTIF(I5:I9,">0") -> 2
A14: Verdict | C14: =IF(C11=0,"Enter source IDs above",IF(C11=1,"Single source: one signal",IF(C12=1,"Echo: every source traces to one root, so this is one signal",IF(OR(C12<C11,C13>0),"Partial: "&C12&" independent roots among "&C11&" sources; some build on others","Independent: "&C12&" separate roots")))) -> Echo: every source traces to one root, so this is one signal
A16: Rule: report confidence from independent roots and data age, not from the number of sources that agree. Use the Verdict wording in the alert's Sources and confidence section.

Sheet Policy Map
A1: Policy map: regulatory and policy levers by commodity, and the sources that cover them
A2: Part 1 lists what to monitor for each commodity (planning notes from general knowledge, not current status). Part 2 checks that every commodity has federal, state and international coverage.
A4: Commodity | B4: Policy and regulatory levers to monitor | C4: Main agencies and bodies | D4: Best first sources (registry IDs)
A5: Dairy | B5: Federal Milk Marketing Order pricing and hearings; Dairy Margin Coverage and farm program rules; school meal, WIC and SNAP rules; export market access and tariff-rate quotas; animal disease rules; manure and methane rules; labor and immigration enforcement; state animal-welfare laws | C5: USDA AMS, FSA, FNS, APHIS; FDA; EPA; DOL; USTR; state legislatures | D5: S079, S078, S087, S083, S086, S089, S097, S054, S093, S051
A6: Grains and oilseeds | B6: ARC/PLC and crop insurance; biofuel rules and tax credits; tariffs and trade deals; pesticide and seed trait approvals; conservation program rules; water and nutrient rules | C6: USDA FSA, RMA, NRCS, APHIS; EPA; Treasury and IRS; USTR; Congress | D6: S078, S075, S037, S090, S085, S083, S088, S097, S054, S102, S103, S104
A7: Livestock (cattle and hogs) | B7: Packers and Stockyards rules; meat inspection and origin labeling; animal disease and import controls; state animal-welfare laws; export market access; environmental rules for large operations | C7: USDA AMS, FSIS, APHIS; EPA; USTR; state legislatures and ballot measures | D7: S081, S082, S083, S101, S096, S093, S086, S105, S106
A8: Poultry and eggs | B8: Avian influenza response and indemnity; inspection and line-speed rules; state cage-free laws; trade bans tied to disease; labor rules | C8: USDA APHIS, FSIS; state legislatures; USTR | D8: S083, S082, S101, S096, S093, S107, S108
A9: Specialty crops | B9: Farm labor and H-2A wage rules; produce safety and traceability; pesticide residue limits; marketing orders; import competition and trade remedies; state water and labor laws | C9: DOL; FDA; EPA; USDA AMS; Commerce; state legislatures | D9: S089, S084, S085, S080, S098, S097, S093, S109
A10: Inputs (fertilizer, chemicals, seed) | B10: Tariffs and antidumping or countervailing duties; nutrient and pesticide rules; antitrust review of input suppliers; energy policy | C10: Commerce; USITC; EPA; DOJ and FTC | D10: S098, S097, S085, S086, S071, S110
A11: Farm economy and ownership | B11: Farm bill funding and timing; tax rules for farm income, equipment and estates; credit programs; foreign and corporate land ownership laws; competition policy | C11: Congress; Treasury and IRS; USDA FSA; state legislatures; DOJ and FTC | D11: S072, S073, S075, S090, S078, S093, S095, S071
A12: All commodities (cross-cutting) | B12: Farm bill and appropriations; executive orders; court rulings; rulemaking calendar and comment periods; trade agreements | C12: Congress; White House OMB; federal courts; USTR | D12: S072, S076, S077, S057, S074, S112, S113, S095
A15: Part 2: Coverage matrix (Y = the source covers that commodity group)
A16: Source ID | B16: Source | C16: Jurisdiction | D16: Dairy | E16: Grains & oilseeds | F16: Livestock & poultry | G16: Specialty crops | H16: Inputs
A17: S027 | B17: =IFERROR(INDEX('Source Registry'!$B$2:$B$300,MATCH(A17,'Source Registry'!$A$2:$A$300,0)),"ID not found") -> FAS GAIN reports | C17: International / US federal | D17: Y | E17: Y | F17: Y | G17: Y
A18: S037 | B18: =IFERROR(INDEX('Source Registry'!$B$2:$B$300,MATCH(A18,'Source Registry'!$A$2:$A$300,0)),"ID not found") -> EPA Renewable Fuel Standard | C18: US federal | E18: Y
A19: S051 | B19: =IFERROR(INDEX('Source Registry'!$B$2:$B$300,MATCH(A19,'Source Registry'!$A$2:$A$300,0)),"ID not found") -> IDFA and NMPF industry analysis | C19: US federal / advocacy | D19: Y
A20: S054 | B20: =IFERROR(INDEX('Source Registry'!$B$2:$B$300,MATCH(A20,'Source Registry'!$A$2:$A$300,0)),"ID not found") -> USTR trade actions | C20: US federal / international | D20: Y | E20: Y | F20: Y | G20: Y | H20: Y
A21: S055 | B21: =IFERROR(INDEX('Source Registry'!$B$2:$B$300,MATCH(A21,'Source Registry'!$A$2:$A$300,0)),"ID not found") -> WTO data and notifications | C21: International | D21: Y | E21: Y | F21: Y | G21: Y | H21: Y
A22: S056 | B22: =IFERROR(INDEX('Source Registry'!$B$2:$B$300,MATCH(A22,'Source Registry'!$A$2:$A$300,0)),"ID not found") -> Global Trade Alert | C22: International | D22: Y | E22: Y | F22: Y | G22: Y | H22: Y
A23: S057 | B23: =IFERROR(INDEX('Source Registry'!$B$2:$B$300,MATCH(A23,'Source Registry'!$A$2:$A$300,0)),"ID not found") -> Federal Register | C23: US federal | D23: Y | E23: Y | F23: Y | G23: Y | H23: Y
A24: S059 | B24: =IFERROR(INDEX('Source Registry'!$B$2:$B$300,MATCH(A24,'Source Registry'!$A$2:$A$300,0)),"ID not found") -> Dietary Guidelines for Americans | C24: US federal | D24: Y | F24: Y | G24: Y
A25: S060 | B25: =IFERROR(INDEX('Source Registry'!$B$2:$B$300,MATCH(A25,'Source Registry'!$A$2:$A$300,0)),"ID not found") -> FDA food regulation and approvals | C25: US federal | D25: Y | E25: Y | F25: Y | G25: Y
A26: S071 | B26: =IFERROR(INDEX('Source Registry'!$B$2:$B$300,MATCH(A26,'Source Registry'!$A$2:$A$300,0)),"ID not found") -> DOJ Antitrust and FTC actions | C26: US federal | D26: Y | E26: Y | F26: Y | G26: Y | H26: Y
A27: S072 | B27: =IFERROR(INDEX('Source Registry'!$B$2:$B$300,MATCH(A27,'Source Registry'!$A$2:$A$300,0)),"ID not found") -> Congress.gov | C27: US federal | D27: Y | E27: Y | F27: Y | G27: Y | H27: Y
A28: S073 | B28: =IFERROR(INDEX('Source Registry'!$B$2:$B$300,MATCH(A28,'Source Registry'!$A$2:$A$300,0)),"ID not found") -> House and Senate Agriculture Committees | C28: US federal | D28: Y | E28: Y | F28: Y | G28: Y | H28: Y
A29: S074 | B29: =IFERROR(INDEX('Source Registry'!$B$2:$B$300,MATCH(A29,'Source Registry'!$A$2:$A$300,0)),"ID not found") -> CRS reports on agriculture policy | C29: US federal | D29: Y | E29: Y | F29: Y | G29: Y | H29: Y
A30: S075 | B30: =IFERROR(INDEX('Source Registry'!$B$2:$B$300,MATCH(A30,'Source Registry'!$A$2:$A$300,0)),"ID not found") -> CBO baseline and farm program cost estimates | C30: US federal | D30: Y | E30: Y | F30: Y
A31: S076 | B31: =IFERROR(INDEX('Source Registry'!$B$2:$B$300,MATCH(A31,'Source Registry'!$A$2:$A$300,0)),"ID not found") -> Regulations.gov dockets | C31: US federal | D31: Y | E31: Y | F31: Y | G31: Y | H31: Y
A32: S077 | B32: =IFERROR(INDEX('Source Registry'!$B$2:$B$300,MATCH(A32,'Source Registry'!$A$2:$A$300,0)),"ID not found") -> Unified Agenda and OIRA review | C32: US federal | D32: Y | E32: Y | F32: Y | G32: Y | H32: Y
A33: S078 | B33: =IFERROR(INDEX('Source Registry'!$B$2:$B$300,MATCH(A33,'Source Registry'!$A$2:$A$300,0)),"ID not found") -> USDA FSA program notices | C33: US federal | D33: Y | E33: Y | F33: Y | G33: Y
A34: S079 | B34: =IFERROR(INDEX('Source Registry'!$B$2:$B$300,MATCH(A34,'Source Registry'!$A$2:$A$300,0)),"ID not found") -> Federal Milk Marketing Orders | C34: US federal | D34: Y
A35: S080 | B35: =IFERROR(INDEX('Source Registry'!$B$2:$B$300,MATCH(A35,'Source Registry'!$A$2:$A$300,0)),"ID not found") -> AMS marketing orders and agreements | C35: US federal | D35: Y | G35: Y
A36: S081 | B36: =IFERROR(INDEX('Source Registry'!$B$2:$B$300,MATCH(A36,'Source Registry'!$A$2:$A$300,0)),"ID not found") -> Packers and Stockyards Act rules and enforcement | C36: US federal | F36: Y
A37: S082 | B37: =IFERROR(INDEX('Source Registry'!$B$2:$B$300,MATCH(A37,'Source Registry'!$A$2:$A$300,0)),"ID not found") -> FSIS rules, labeling and inspection policy | C37: US federal | F37: Y
A38: S083 | B38: =IFERROR(INDEX('Source Registry'!$B$2:$B$300,MATCH(A38,'Source Registry'!$A$2:$A$300,0)),"ID not found") -> APHIS regulations (animal disease, plant health, biotechnology) | C38: US federal | D38: Y | E38: Y | F38: Y | G38: Y
A39: S084 | B39: =IFERROR(INDEX('Source Registry'!$B$2:$B$300,MATCH(A39,'Source Registry'!$A$2:$A$300,0)),"ID not found") -> FDA Food Safety Modernization Act rules | C39: US federal | D39: Y | G39: Y
A40: S085 | B40: =IFERROR(INDEX('Source Registry'!$B$2:$B$300,MATCH(A40,'Source Registry'!$A$2:$A$300,0)),"ID not found") -> EPA pesticide program | C40: US federal | E40: Y | G40: Y
A41: S086 | B41: =IFERROR(INDEX('Source Registry'!$B$2:$B$300,MATCH(A41,'Source Registry'!$A$2:$A$300,0)),"ID not found") -> EPA agriculture and water, air and nutrient rules | C41: US federal | D41: Y | E41: Y | F41: Y | G41: Y | H41: Y
A42: S087 | B42: =IFERROR(INDEX('Source Registry'!$B$2:$B$300,MATCH(A42,'Source Registry'!$A$2:$A$300,0)),"ID not found") -> USDA FNS nutrition program rules | C42: US federal | D42: Y | F42: Y | G42: Y
A43: S088 | B43: =IFERROR(INDEX('Source Registry'!$B$2:$B$300,MATCH(A43,'Source Registry'!$A$2:$A$300,0)),"ID not found") -> NRCS conservation programs | C43: US federal | D43: Y | E43: Y | F43: Y | G43: Y
A44: S089 | B44: =IFERROR(INDEX('Source Registry'!$B$2:$B$300,MATCH(A44,'Source Registry'!$A$2:$A$300,0)),"ID not found") -> DOL farm labor and H-2A rules | C44: US federal | D44: Y | E44: Y | F44: Y | G44: Y
A45: S090 | B45: =IFERROR(INDEX('Source Registry'!$B$2:$B$300,MATCH(A45,'Source Registry'!$A$2:$A$300,0)),"ID not found") -> IRS and Treasury guidance for farms | C45: US federal | D45: Y | E45: Y | F45: Y | G45: Y | H45: Y
A46: S091 | B46: =IFERROR(INDEX('Source Registry'!$B$2:$B$300,MATCH(A46,'Source Registry'!$A$2:$A$300,0)),"ID not found") -> ERS Farm and Commodity Policy | C46: US federal | D46: Y | E46: Y | F46: Y | G46: Y | H46: Y
A47: S092 | B47: =IFERROR(INDEX('Source Registry'!$B$2:$B$300,MATCH(A47,'Source Registry'!$A$2:$A$300,0)),"ID not found") -> NCSL agriculture and rural development tracker | C47: US state | D47: Y | E47: Y | F47: Y | G47: Y | H47: Y
A48: S093 | B48: =IFERROR(INDEX('Source Registry'!$B$2:$B$300,MATCH(A48,'Source Registry'!$A$2:$A$300,0)),"ID not found") -> LegiScan | C48: US state | D48: Y | E48: Y | F48: Y | G48: Y | H48: Y
A49: S094 | B49: =IFERROR(INDEX('Source Registry'!$B$2:$B$300,MATCH(A49,'Source Registry'!$A$2:$A$300,0)),"ID not found") -> NASDA | C49: US state | D49: Y | E49: Y | F49: Y | G49: Y | H49: Y
A50: S095 | B50: =IFERROR(INDEX('Source Registry'!$B$2:$B$300,MATCH(A50,'Source Registry'!$A$2:$A$300,0)),"ID not found") -> National Agricultural Law Center | C50: US federal and state | D50: Y | E50: Y | F50: Y | G50: Y | H50: Y
A51: S096 | B51: =IFERROR(INDEX('Source Registry'!$B$2:$B$300,MATCH(A51,'Source Registry'!$A$2:$A$300,0)),"ID not found") -> Ballotpedia agriculture ballot measures | C51: US state | F51: Y
A52: S097 | B52: =IFERROR(INDEX('Source Registry'!$B$2:$B$300,MATCH(A52,'Source Registry'!$A$2:$A$300,0)),"ID not found") -> USITC tariff schedule (HTS) and trade remedies | C52: US federal / international | D52: Y | E52: Y | F52: Y | G52: Y | H52: Y
A53: S098 | B53: =IFERROR(INDEX('Source Registry'!$B$2:$B$300,MATCH(A53,'Source Registry'!$A$2:$A$300,0)),"ID not found") -> Commerce AD/CVD enforcement | C53: US federal / international | G53: Y | H53: Y
A54: S099 | B54: =IFERROR(INDEX('Source Registry'!$B$2:$B$300,MATCH(A54,'Source Registry'!$A$2:$A$300,0)),"ID not found") -> EU Common Agricultural Policy and EUR-Lex | C54: International | D54: Y | E54: Y | F54: Y | G54: Y
A55: S100 | B55: =IFERROR(INDEX('Source Registry'!$B$2:$B$300,MATCH(A55,'Source Registry'!$A$2:$A$300,0)),"ID not found") -> Codex Alimentarius | C55: International | D55: Y | E55: Y | F55: Y | G55: Y
A56: S101 | B56: =IFERROR(INDEX('Source Registry'!$B$2:$B$300,MATCH(A56,'Source Registry'!$A$2:$A$300,0)),"ID not found") -> WOAH animal health standards and disease reports | C56: International | D56: Y | F56: Y
A57: S102 | B57: =IFERROR(INDEX('Source Registry'!$B$2:$B$300,MATCH(A57,'Source Registry'!$A$2:$A$300,0)),"ID not found") -> National Corn Growers Association | C57: US federal | E57: Y
A58: S103 | B58: =IFERROR(INDEX('Source Registry'!$B$2:$B$300,MATCH(A58,'Source Registry'!$A$2:$A$300,0)),"ID not found") -> American Soybean Association | C58: US federal | E58: Y
A59: S104 | B59: =IFERROR(INDEX('Source Registry'!$B$2:$B$300,MATCH(A59,'Source Registry'!$A$2:$A$300,0)),"ID not found") -> National Association of Wheat Growers | C59: US federal | E59: Y
A60: S105 | B60: =IFERROR(INDEX('Source Registry'!$B$2:$B$300,MATCH(A60,'Source Registry'!$A$2:$A$300,0)),"ID not found") -> NCBA policy | C60: US federal | F60: Y
A61: S106 | B61: =IFERROR(INDEX('Source Registry'!$B$2:$B$300,MATCH(A61,'Source Registry'!$A$2:$A$300,0)),"ID not found") -> National Pork Producers Council | C61: US federal and state | F61: Y
A62: S107 | B62: =IFERROR(INDEX('Source Registry'!$B$2:$B$300,MATCH(A62,'Source Registry'!$A$2:$A$300,0)),"ID not found") -> National Chicken Council | C62: US federal | F62: Y
A63: S108 | B63: =IFERROR(INDEX('Source Registry'!$B$2:$B$300,MATCH(A63,'Source Registry'!$A$2:$A$300,0)),"ID not found") -> United Egg Producers | C63: US federal and state | F63: Y
A64: S109 | B64: =IFERROR(INDEX('Source Registry'!$B$2:$B$300,MATCH(A64,'Source Registry'!$A$2:$A$300,0)),"ID not found") -> Western Growers | C64: US federal and state | G64: Y
A65: S110 | B65: =IFERROR(INDEX('Source Registry'!$B$2:$B$300,MATCH(A65,'Source Registry'!$A$2:$A$300,0)),"ID not found") -> The Fertilizer Institute | C65: US federal | H65: Y
A66: S111 | B66: =IFERROR(INDEX('Source Registry'!$B$2:$B$300,MATCH(A66,'Source Registry'!$A$2:$A$300,0)),"ID not found") -> American Farm Bureau Federation | C66: US federal and state | D66: Y | E66: Y | F66: Y | G66: Y | H66: Y
A67: S112 | B67: =IFERROR(INDEX('Source Registry'!$B$2:$B$300,MATCH(A67,'Source Registry'!$A$2:$A$300,0)),"ID not found") -> Agri-Pulse | C67: US federal | D67: Y | E67: Y | F67: Y | G67: Y | H67: Y
A68: S113 | B68: =IFERROR(INDEX('Source Registry'!$B$2:$B$300,MATCH(A68,'Source Registry'!$A$2:$A$300,0)),"ID not found") -> Hagstrom Report | C68: US federal | D68: Y | E68: Y | F68: Y | G68: Y | H68: Y
A70: Total sources covering the group | D70: =COUNTIF(D17:D68,"Y") -> 37 | E70: =COUNTIF(E17:E68,"Y") -> 35 | F70: =COUNTIF(F17:F68,"Y") -> 40 | G70: =COUNTIF(G17:G68,"Y") -> 36 | H70: =COUNTIF(H17:H68,"Y") -> 23
A71: of which US federal | D71: =COUNTIFS(D17:D68,"Y",$C17:$C68,"US federal*") -> 28 | E71: =COUNTIFS(E17:E68,"Y",$C17:$C68,"US federal*") -> 27 | F71: =COUNTIFS(F17:F68,"Y",$C17:$C68,"US federal*") -> 30 | G71: =COUNTIFS(G17:G68,"Y",$C17:$C68,"US federal*") -> 28 | H71: =COUNTIFS(H17:H68,"Y",$C17:$C68,"US federal*") -> 18
A72: of which US state | D72: =COUNTIFS(D17:D68,"Y",$C17:$C68,"*state*") -> 5 | E72: =COUNTIFS(E17:E68,"Y",$C17:$C68,"*state*") -> 5 | F72: =COUNTIFS(F17:F68,"Y",$C17:$C68,"*state*") -> 8 | G72: =COUNTIFS(G17:G68,"Y",$C17:$C68,"*state*") -> 6 | H72: =COUNTIFS(H17:H68,"Y",$C17:$C68,"*state*") -> 5
A73: of which international | D73: =COUNTIFS(D17:D68,"Y",$C17:$C68,"*international*") -> 8 | E73: =COUNTIFS(E17:E68,"Y",$C17:$C68,"*international*") -> 7 | F73: =COUNTIFS(F17:F68,"Y",$C17:$C68,"*international*") -> 8 | G73: =COUNTIFS(G17:G68,"Y",$C17:$C68,"*international*") -> 8 | H73: =COUNTIFS(H17:H68,"Y",$C17:$C68,"*international*") -> 5
A74: Coverage check (federal, state and international all above zero) | D74: =IF(AND(D71>0,D72>0,D73>0),"Covered","Gap") -> Covered | E74: =IF(AND(E71>0,E72>0,E73>0),"Covered","Gap") -> Covered | F74: =IF(AND(F71>0,F72>0,F73>0),"Covered","Gap") -> Covered | G74: =IF(AND(G71>0,G72>0,G73>0),"Covered","Gap") -> Covered | H74: =IF(AND(H71>0,H72>0,H73>0),"Covered","Gap") -> Covered
A76: Notes: flags are judgments from general knowledge of each source's scope. Jurisdiction words match counts: a source marked 'US federal and state' counts in both rows. Cross-check scope on each source's site before relying on it.

Sheet Policy Alert Rules
A1: Policy alert rules: when a policy or regulatory item becomes an alert
A2: Each rule watches one stage of how a policy moves, from planned to effective. Edit the yellow thresholds; the trigger text updates. Policy and regulation is its own trigger family; each alert states a near-term and a longer-term impact, with long-term context from the driver briefs.
A4: Comment-deadline window (days) | B4: 14 | C4: A rule moves to High urgency when its comment deadline falls inside this window
A5: Program-deadline window (days) | B5: 30 | C5: Sign-up and program deadlines alert when this close
A6: Effective-date lead (days) | B6: 60 | C6: Final rules alert again this many days before they take effect
A9: # | B9: Stage | C9: Trigger the agent watches for | D9: Primary source ID | E9: Primary source | F9: Also watch (IDs) | G9: Default urgency | H9: Typical lead time | I9: The alert must say
A10: 1 | B10: Rule planned | C10: A rule that touches the farm's commodities appears on the Unified Agenda or goes to White House review | D10: S077 | E10: =IFERROR(INDEX('Source Registry'!$B$2:$B$300,MATCH(D10,'Source Registry'!$A$2:$A$300,0)),"ID not found") -> Unified Agenda and OIRA review | F10: S057, S076 | G10: Watch | H10: Months | I10: Which rule, expected timing, who is affected, and what it could change
A11: 2 | B11: Bill moves | C11: A farm bill or related bill is introduced, marked up, or passes a chamber | D11: S072 | E11: =IFERROR(INDEX('Source Registry'!$B$2:$B$300,MATCH(D11,'Source Registry'!$A$2:$A$300,0)),"ID not found") -> Congress.gov | F11: S073, S074, S075 | G11: Watch (High at markup or floor vote) | H11: Weeks to months | I11: What the bill would change for the farm's programs, income, or costs, and the next vote
A12: 3 | B12: Proposed rule published | C12: A proposed rule is published for the farm's commodity groups | D12: S057 | E12: =IFERROR(INDEX('Source Registry'!$B$2:$B$300,MATCH(D12,'Source Registry'!$A$2:$A$300,0)),"ID not found") -> Federal Register | F12: S076, S082, S083, S085, S079 | G12: High | H12: Weeks | I12: Plain-language summary of the change, comment deadline, and how to comment
A13: 4 | B13: Comment period closing | C13: ="A docket tied to the farm closes comments within "&$B$4&" days" -> A docket tied to the farm closes comments within 14 days | D13: S076 | E13: =IFERROR(INDEX('Source Registry'!$B$2:$B$300,MATCH(D13,'Source Registry'!$A$2:$A$300,0)),"ID not found") -> Regulations.gov dockets | F13: S057, S095 | G13: High | H13: Days to weeks | I13: Deadline, what the proposal would do to this farm, and whether to submit a comment
A14: 5 | B14: Final rule or effective date | C14: ="A final rule is published, or takes effect within "&$B$6&" days" -> A final rule is published, or takes effect within 60 days | D14: S057 | E14: =IFERROR(INDEX('Source Registry'!$B$2:$B$300,MATCH(D14,'Source Registry'!$A$2:$A$300,0)),"ID not found") -> Federal Register | F14: S076, S091, S074 | G14: High | H14: Weeks to months | I14: Effective date, compliance steps, and cost or income effect
A15: 6 | B15: Program notice or sign-up | C15: ="A program sign-up, payment rule, or deadline falls within "&$B$5&" days" -> A program sign-up, payment rule, or deadline falls within 30 days | D15: S078 | E15: =IFERROR(INDEX('Source Registry'!$B$2:$B$300,MATCH(D15,'Source Registry'!$A$2:$A$300,0)),"ID not found") -> USDA FSA program notices | F15: S088, S080, S087 | G15: High | H15: Weeks | I15: Program, eligibility, deadline, and the action required
A16: 7 | B16: Pricing or marketing order decision | C16: A milk marketing order hearing, decision, or amendment, or a marketing order change for another commodity | D16: S079 | E16: =IFERROR(INDEX('Source Registry'!$B$2:$B$300,MATCH(D16,'Source Registry'!$A$2:$A$300,0)),"ID not found") -> Federal Milk Marketing Orders | F16: S080 | G16: High (dairy) | H16: Weeks to months | I16: What changes in the pricing formula or program and its effect on the farm's pay price
A17: 8 | B17: Trade action | C17: A tariff, quota, retaliation, ban, or new import rule by the US or a major buyer | D17: S054 | E17: =IFERROR(INDEX('Source Registry'!$B$2:$B$300,MATCH(D17,'Source Registry'!$A$2:$A$300,0)),"ID not found") -> USTR trade actions | F17: S097, S098, S056, S027 | G17: High | H17: Days to weeks | I17: Product, countries, effective date, and which of the farm's products or inputs are affected
A18: 9 | B18: Animal or plant disease measure | C18: A new movement restriction, import ban, or indemnity rule tied to disease | D18: S083 | E18: =IFERROR(INDEX('Source Registry'!$B$2:$B$300,MATCH(D18,'Source Registry'!$A$2:$A$300,0)),"ID not found") -> APHIS regulations (animal disease, plant health, biotechnology) | F18: S101, S027 | G18: Urgent | H18: Same day to days | I18: What is restricted, where, and what the farm should confirm now
A19: 10 | B19: State bill or ballot measure | C19: A state bill advances or a ballot measure is certified in the farm's state or in a state of a major buyer | D19: S093 | E19: =IFERROR(INDEX('Source Registry'!$B$2:$B$300,MATCH(D19,'Source Registry'!$A$2:$A$300,0)),"ID not found") -> LegiScan | F19: S092, S096, S095 | G19: Watch (High near a vote) | H19: Weeks to months | I19: State, bill or measure, status, and how it would change farm operations or market access
A20: 11 | B20: Court ruling | C20: A court ruling blocks, upholds, or changes a rule or law the farm is exposed to | D20: S095 | E20: =IFERROR(INDEX('Source Registry'!$B$2:$B$300,MATCH(D20,'Source Registry'!$A$2:$A$300,0)),"ID not found") -> National Agricultural Law Center | F20: S074, S057 | G20: High | H20: Days | I20: Which rule, what the court held, and whether the rule is in effect now
A21: 12 | B21: Tax or credit guidance | C21: Treasury or IRS guidance on farm income, equipment, estates, or clean fuel credits | D21: S090 | E21: =IFERROR(INDEX('Source Registry'!$B$2:$B$300,MATCH(D21,'Source Registry'!$A$2:$A$300,0)),"ID not found") -> IRS and Treasury guidance for farms | F21: S057, S075 | G21: Watch | H21: Months | I21: What changes, the tax year it applies to, and the farm's exposure
A22: 13 | B22: Food and health policy | C22: Dietary guideline, nutrition program, or food rule changes that shift demand | D22: S060 | E22: =IFERROR(INDEX('Source Registry'!$B$2:$B$300,MATCH(D22,'Source Registry'!$A$2:$A$300,0)),"ID not found") -> FDA food regulation and approvals | F22: S059, S087, S084 | G22: Watch | H22: Months to years | I22: What demand it shifts, for which products, and how soon
A23: 14 | B23: Foreign regulation | C23: A foreign import standard or sustainability rule that affects exports | D23: S099 | E23: =IFERROR(INDEX('Source Registry'!$B$2:$B$300,MATCH(D23,'Source Registry'!$A$2:$A$300,0)),"ID not found") -> EU Common Agricultural Policy and EUR-Lex | F23: S100, S027 | G23: Watch | H23: Months | I23: Country, product, rule, and date it applies
A24: 15 | B24: Competition action | C24: An antitrust or Packers and Stockyards action involving a buyer, processor, or input supplier | D24: S071 | E24: =IFERROR(INDEX('Source Registry'!$B$2:$B$300,MATCH(D24,'Source Registry'!$A$2:$A$300,0)),"ID not found") -> DOJ Antitrust and FTC actions | F24: S081 | G24: Watch | H24: Months | I24: Who, what is alleged or ordered, and the possible effect on the farm's buyers or costs
A26: Routing and quality rules
A27: Commodity routing | C27: Send an item only to farms whose commodity groups it covers, using the Policy Map coverage flags.
A28: Geography | C28: State items go to farms in that state and to farms whose major buyers are there. Federal items go to all matching farms.
A29: One thread per item | C29: A later stage updates the same alert thread (planned, proposed, final, effective) instead of creating a new alert.
A30: Confirm with the official record | C30: High and Urgent alerts need a Tier 1 source (Federal Register, agency notice, Congress.gov, court record). Items seen only in news or advocacy sources are sent as 'unconfirmed' and count as echoes in the independence check.
A31: Fit check | C31: Every alert includes Fit with this farm: strengths, values, near-term and long-term goals, and share of income affected. Low-fit items get one line in the weekly brief.
A32: Human review | C32: At launch a person reviews every Urgent alert and every High alert before it goes out.
A33: Uncertainty | C33: Say when a rule is proposed and not final, and when the outcome depends on a vote or court ruling. Do not state a probability unless a source gives one.

Sheet Coverage Checklist
A1: Coverage checklist: what the registry should cover, and where gaps remain
A2: Each row is a kind of information the agent should be able to see. Source IDs are typed in; the count and status are formulas. Add IDs as you add sources. Gap = none; Thin = one.
A4: Covered | B4: =COUNTIF(F8:F73,"Covered") -> 49
A5: Thin (one source) | B5: =COUNTIF(F8:F73,"Thin") -> 16
A6: Gap (none) | B6: =COUNTIF(F8:F73,"Gap") -> 1
A7: Driver | B7: What the agent needs to see | C7: Why it matters | D7: Source IDs | E7: Sources | F7: Status
A8: Climate Volatility | B8: Short-range forecasts and weather alerts | C8: Frost, heat, storms, and planting or harvest windows | D8: S114, S127, S131, S132 | E8: =IF(D8="",0,LEN(D8)-LEN(SUBSTITUTE(D8,",",""))+1) -> 4 | F8: =IF(E8=0,"Gap",IF(E8=1,"Thin","Covered")) -> Covered
A9: Climate Volatility | B9: Seasonal outlooks | C9: Season-level risk to yield, forage, and heat stress | D9: S064, S130, S066 | E9: =IF(D9="",0,LEN(D9)-LEN(SUBSTITUTE(D9,",",""))+1) -> 3 | F9: =IF(E9=0,"Gap",IF(E9=1,"Thin","Covered")) -> Covered
A10: Climate Volatility | B10: Climate drivers (ENSO) | C10: Early read on seasonal patterns | D10: S116, S130 | E10: =IF(D10="",0,LEN(D10)-LEN(SUBSTITUTE(D10,",",""))+1) -> 2 | F10: =IF(E10=0,"Gap",IF(E10=1,"Thin","Covered")) -> Covered
A11: Climate Volatility | B11: Drought status and conditions | C11: Current stress on crops and pasture | D11: S065, S117, S004 | E11: =IF(D11="",0,LEN(D11)-LEN(SUBSTITUTE(D11,",",""))+1) -> 3 | F11: =IF(E11=0,"Gap",IF(E11=1,"Thin","Covered")) -> Covered
A12: Climate Volatility | B12: Historical weather and normals | C12: How unusual a season is | D12: S115, S123, S119 | E12: =IF(D12="",0,LEN(D12)-LEN(SUBSTITUTE(D12,",",""))+1) -> 3 | F12: =IF(E12=0,"Gap",IF(E12=1,"Thin","Covered")) -> Covered
A13: Climate Volatility | B13: Soil moisture and field-level conditions | C13: Planting and yield risk at the farm | D13: S119, S123 | E13: =IF(D13="",0,LEN(D13)-LEN(SUBSTITUTE(D13,",",""))+1) -> 2 | F13: =IF(E13=0,"Gap",IF(E13=1,"Thin","Covered")) -> Covered
A14: Climate Volatility | B14: Water supply, snowpack, and streamflow | C14: Irrigation and livestock water | D14: S120, S121, S122, S133 | E14: =IF(D14="",0,LEN(D14)-LEN(SUBSTITUTE(D14,",",""))+1) -> 4 | F14: =IF(E14=0,"Gap",IF(E14=1,"Thin","Covered")) -> Covered
A15: Climate Volatility | B15: Extreme events: hurricane, wildfire, flood | C15: Sudden losses and logistics disruption | D15: S124, S125, S133 | E15: =IF(D15="",0,LEN(D15)-LEN(SUBSTITUTE(D15,",",""))+1) -> 3 | F15: =IF(E15=0,"Gap",IF(E15=1,"Thin","Covered")) -> Covered
A16: Climate Volatility | B16: Long-term climate projections | C16: Multi-year planning | D16: S128, S129, S118, S066 | E16: =IF(D16="",0,LEN(D16)-LEN(SUBSTITUTE(D16,",",""))+1) -> 4 | F16: =IF(E16=0,"Gap",IF(E16=1,"Thin","Covered")) -> Covered
A17: Climate Volatility | B17: Crop prospects and food security abroad | C17: Competitor supply and buyer stress | D17: S067 | E17: =IF(D17="",0,LEN(D17)-LEN(SUBSTITUTE(D17,",",""))+1) -> 1 | F17: =IF(E17=0,"Gap",IF(E17=1,"Thin","Covered")) -> Thin
A18: Climate Volatility | B18: Insurance and disaster assistance | C18: Loss recovery and program eligibility | D18: S068, S126 | E18: =IF(D18="",0,LEN(D18)-LEN(SUBSTITUTE(D18,",",""))+1) -> 2 | F18: =IF(E18=0,"Gap",IF(E18=1,"Thin","Covered")) -> Covered
A19: Climate Volatility | B19: Satellite crop condition and yield estimates | C19: Independent yield read | D19: S171 | E19: =IF(D19="",0,LEN(D19)-LEN(SUBSTITUTE(D19,",",""))+1) -> 1 | F19: =IF(E19=0,"Gap",IF(E19=1,"Thin","Covered")) -> Thin
... A60: Core S&D (baseline) | B60: Labor | C60: Farm wage and labor supply | D60: S151, S089 | E60: =IF(D60="",0,LEN(D60)-LEN(SUBSTITUTE(D60,",",""))+1) -> 2 | F60: =IF(E60=0,"Gap",IF(E60=1,"Thin","Covered")) -> Covered
A61: Core S&D (baseline) | B61: Local buyer and processor pay prices | C61: The farm's own price, not a regional average | E61: =IF(D61="",0,LEN(D61)-LEN(SUBSTITUTE(D61,",",""))+1) -> 0 | F61: =IF(E61=0,"Gap",IF(E61=1,"Thin","Covered")) -> Gap
A62: Core S&D (baseline) | B62: Retail and farm-input local prices | C62: Prices the farm actually pays | D62: S041 | E62: =IF(D62="",0,LEN(D62)-LEN(SUBSTITUTE(D62,",",""))+1) -> 1 | F62: =IF(E62=0,"Gap",IF(E62=1,"Thin","Covered")) -> Thin
A63: Lens | B63: Operation characteristics by location (soil, crop history, climate zone, flood risk) | C63: Prefills the strategic lens for any farm | D63: S169, S170, S172, S173 | E63: =IF(D63="",0,LEN(D63)-LEN(SUBSTITUTE(D63,",",""))+1) -> 4 | F63: =IF(E63=0,"Gap",IF(E63=1,"Thin","Covered")) -> Covered
A64: Legacy | B64: Succession, transfer, and beginning-farmer resources | C64: Legacy is the ultimate aim for most family farms | D64: S174, S175, S176, S014, S095, S078 | E64: =IF(D64="",0,LEN(D64)-LEN(SUBSTITUTE(D64,",",""))+1) -> 6 | F64: =IF(E64=0,"Gap",IF(E64=1,"Thin","Covered")) -> Covered
A65: Tier 0 | B65: Synthesized house context (driver briefs and Future State material) | C65: The lay of the land every update reads first | D65: S159, S160, S161, S162, S163, S164, S165, S166 | E65: =IF(D65="",0,LEN(D65)-LEN(SUBSTITUTE(D65,",",""))+1) -> 8 | F65: =IF(E65=0,"Gap",IF(E65=1,"Thin","Covered")) -> Covered
A66: Tier 0 | B66: Diversification path library and case examples | C66: Base for diversification-path triggers | D66: S167, S168 | E66: =IF(D66="",0,LEN(D66)-LEN(SUBSTITUTE(D66,",",""))+1) -> 2 | F66: =IF(E66=0,"Gap",IF(E66=1,"Thin","Covered")) -> Covered
A67: Human Health | B67: GLP-1 adoption, access, and pricing | C67: Central thread for Human Health | D67: S177, S178, S179, S180, S141 | E67: =IF(D67="",0,LEN(D67)-LEN(SUBSTITUTE(D67,",",""))+1) -> 5 | F67: =IF(E67=0,"Gap",IF(E67=1,"Thin","Covered")) -> Covered
A68: Human Health | B68: Premium, organic, and whole-food demand | C68: Where health-driven spending is going | D68: S181, S063, S140 | E68: =IF(D68="",0,LEN(D68)-LEN(SUBSTITUTE(D68,",",""))+1) -> 3 | F68: =IF(E68=0,"Gap",IF(E68=1,"Thin","Covered")) -> Covered
A69: Climate Volatility | B69: Disaster loss tracking and decadal warming outlooks | C69: Who bears weather losses and how fast risk is rising | D69: S182, S183, S068 | E69: =IF(D69="",0,LEN(D69)-LEN(SUBSTITUTE(D69,",",""))+1) -> 3 | F69: =IF(E69=0,"Gap",IF(E69=1,"Thin","Covered")) -> Covered
A70: Ownership | B70: Investor ownership and operator financial stress | C70: The owner and operator gap | D70: S184, S185, S015, S046, S146 | E70: =IF(D70="",0,LEN(D70)-LEN(SUBSTITUTE(D70,",",""))+1) -> 5 | F70: =IF(E70=0,"Gap",IF(E70=1,"Thin","Covered")) -> Covered
A71: Global Affluence | B71: Consumer class growth forecasts | C71: Pace and location of new demand | D71: S186, S052, S142 | E71: =IF(D71="",0,LEN(D71)-LEN(SUBSTITUTE(D71,",",""))+1) -> 3 | F71: =IF(E71=0,"Gap",IF(E71=1,"Thin","Covered")) -> Covered
A72: Technology | B72: Farm technology adoption surveys | C72: Proven return versus hype | D72: S188, S045, S134 | E72: =IF(D72="",0,LEN(D72)-LEN(SUBSTITUTE(D72,",",""))+1) -> 3 | F72: =IF(E72=0,"Gap",IF(E72=1,"Thin","Covered")) -> Covered
A73: Geopolitics | B73: Competitor export pace (Brazil) | C73: Share lost or gained by U.S. exporters | D73: S187, S038, S026 | E73: =IF(D73="",0,LEN(D73)-LEN(SUBSTITUTE(D73,",",""))+1) -> 3 | F73: =IF(E73=0,"Gap",IF(E73=1,"Thin","Covered")) -> Covered

Sheet Lens to Sources
A1: Lens to sources: how a farm's strategic lens selects its watch list
A2: The Lens Agent builds each farm's watch profile from the lens, usually 15 to 25 sources. It starts with retrieval tier 0, then tier 1, and adds tier 2 detection feeds for the farm's triggers.
A4: Lens element | B4: What it selects | C4: How the registry is filtered | D4: Example registry IDs
A5: Enterprises and income shares | B5: Commodity sources and price and input triggers | C5: Commodity group matches an enterprise; trigger family Price and market or Input cost | D5: S017, S022, S023, S005, S153
A6: Location (state and county) | B6: Regional weather, state policy, local prices | C6: Lens selector names Location; trigger family Weather and climate; state policy sources | D6: S065, S114, S093, S092
A7: Operation characteristics (soil, water, climate zone) | B7: Agronomic and water sources; lens prefill | C7: System role Lens prefill; trigger family Weather and climate | D7: S169, S172, S121, S120
A8: Size class | B8: Fit-appropriate paths and programs | C8: Diversification library; program sources | D8: S167, S175, S078
A9: Goals, advantage, and values | B9: Priority weights for triggers and framing for updates | C9: Trigger families tied to the goal topic | D9: Varies by farm
A10: Legacy intent | B10: Succession, tax, land, and credit sources | C10: Trigger families Land and ownership, Credit and finance, and Policy and regulation (tax) | D10: S174, S175, S176, S014, S015, S046
A11: MFP priority areas (completed farms) | B11: Source topics by dimension | C11: MFP dimension served column (table below) | D11: See table below
A12: MFP SWOT threats and opportunities | B12: Watch topics | C12: Trigger family named by the SWOT item | D12: S054, S097, S025, S098
A13: Farmer requests | B13: Added sources or topics | C13: Added by hand | D13: Varies by farm
A15: MFP dimension to trigger families
A16: MFP dimension | B16: Trigger families and source groups that help | C16: Registry sources serving it
A17: Financial Analysis | B17: Input cost, Credit and finance, Land and ownership | C17: =COUNTIF('Source Registry'!$Y$2:$Y$400,"*"&A17&"*") -> 17
A18: Market Analysis | B18: Price and market, Trade and geopolitics, context sources | C18: =COUNTIF('Source Registry'!$Y$2:$Y$400,"*"&A18&"*") -> 82
A19: Income Diversification | B19: Policy and regulation, Diversification-path viability | C19: =COUNTIF('Source Registry'!$Y$2:$Y$400,"*"&A19&"*") -> 45
A20: Competitive Advantage | B20: Technology and structure | C20: =COUNTIF('Source Registry'!$Y$2:$Y$400,"*"&A20&"*") -> 9
A21: Adoption & Efficiency | B21: Input cost, Technology and structure | C21: =COUNTIF('Source Registry'!$Y$2:$Y$400,"*"&A21&"*") -> 14
A22: Risk & Protection | B22: Weather and climate, Disease and border, Policy and regulation, Credit and finance | C22: =COUNTIF('Source Registry'!$Y$2:$Y$400,"*"&A22&"*") -> 81
A23: Succession | B23: Land and ownership, with legacy and tax sources | C23: =COUNTIF('Source Registry'!$Y$2:$Y$400,"*"&A23&"*") -> 6
A24: Strategic Vision | B24: Context sources and the driver briefs | C24: =COUNTIF('Source Registry'!$Y$2:$Y$400,"*"&A24&"*") -> 54
A25: Records & Data | B25: Lens prefill sources | C25: =COUNTIF('Source Registry'!$Y$2:$Y$400,"*"&A25&"*") -> 4

Sheet Trigger Map
A1: Trigger map: the fast layer that starts updates
A2: Drivers are the slower backdrop. Triggers are the dynamic changes that start an update, and each carries a near-term and a longer-term impact. Counts are formulas over the Source Registry.
A4: Trigger family | B4: Examples | C4: Sources | D4: Detection feeds | E4: Context sources | F4: Matched to the farm by | G4: MFP dimension served
A5: Price and market | B5: Commodity or product price move, futures curve shape, margin spread, basis | C5: =COUNTIF('Source Registry'!$U$2:$U$400,$A5) -> 10 | D5: =COUNTIFS('Source Registry'!$U$2:$U$400,$A5,'Source Registry'!$V$2:$V$400,"Detection feed") -> 8 | E5: =COUNTIFS('Source Registry'!$U$2:$U$400,$A5,'Source Registry'!$V$2:$V$400,"Context")+COUNTIFS('Source Registry'!$U$2:$U$400,$A5,'Source Registry'!$V$2:$V$400,"Context (synthesized)") -> 0 | F5: Enterprises and income shares | G5: Market Analysis
A6: Input cost | B6: Fertilizer, feed, hay, fuel, energy outlook | C6: =COUNTIF('Source Registry'!$U$2:$U$400,$A6) -> 5 | D6: =COUNTIFS('Source Registry'!$U$2:$U$400,$A6,'Source Registry'!$V$2:$V$400,"Detection feed") -> 2 | E6: =COUNTIFS('Source Registry'!$U$2:$U$400,$A6,'Source Registry'!$V$2:$V$400,"Context")+COUNTIFS('Source Registry'!$U$2:$U$400,$A6,'Source Registry'!$V$2:$V$400,"Context (synthesized)") -> 0 | F6: Cost structure and enterprises | G6: Financial Analysis; Adoption & Efficiency
A7: Policy and regulation | B7: A rule planned, proposed, in comment, final, or effective; a bill moving; a program sign-up; a court ruling; a state law; tax guidance | C7: =COUNTIF('Source Registry'!$U$2:$U$400,$A7) -> 44 | D7: =COUNTIFS('Source Registry'!$U$2:$U$400,$A7,'Source Registry'!$V$2:$V$400,"Detection feed") -> 23 | E7: =COUNTIFS('Source Registry'!$U$2:$U$400,$A7,'Source Registry'!$V$2:$V$400,"Context")+COUNTIFS('Source Registry'!$U$2:$U$400,$A7,'Source Registry'!$V$2:$V$400,"Context (synthesized)") -> 18 | F7: Enterprises, size class, and diversification paths | G7: Risk & Protection; Income Diversification
A8: Trade and geopolitics | B8: Tariff, quota, ban, buyer review, shipping disruption, foreign import rule | C8: =COUNTIF('Source Registry'!$U$2:$U$400,$A8) -> 18 | D8: =COUNTIFS('Source Registry'!$U$2:$U$400,$A8,'Source Registry'!$V$2:$V$400,"Detection feed") -> 11 | E8: =COUNTIFS('Source Registry'!$U$2:$U$400,$A8,'Source Registry'!$V$2:$V$400,"Context")+COUNTIFS('Source Registry'!$U$2:$U$400,$A8,'Source Registry'!$V$2:$V$400,"Context (synthesized)") -> 1 | F8: Products sold, buyers, and inputs bought | G8: Market Analysis
A9: Weather and climate | B9: Seasonal outlook shift, drought change, extreme-event forecast, water supply | C9: =COUNTIF('Source Registry'!$U$2:$U$400,$A9) -> 28 | D9: =COUNTIFS('Source Registry'!$U$2:$U$400,$A9,'Source Registry'!$V$2:$V$400,"Detection feed") -> 16 | E9: =COUNTIFS('Source Registry'!$U$2:$U$400,$A9,'Source Registry'!$V$2:$V$400,"Context")+COUNTIFS('Source Registry'!$U$2:$U$400,$A9,'Source Registry'!$V$2:$V$400,"Context (synthesized)") -> 5 | F9: Location and operation characteristics (soil, water, climate zone) | G9: Risk & Protection
A10: Disease and border | B10: Detection nearby, movement rules, import bans | C10: =COUNTIF('Source Registry'!$U$2:$U$400,$A10) -> 3 | D10: =COUNTIFS('Source Registry'!$U$2:$U$400,$A10,'Source Registry'!$V$2:$V$400,"Detection feed") -> 3 | E10: =COUNTIFS('Source Registry'!$U$2:$U$400,$A10,'Source Registry'!$V$2:$V$400,"Context")+COUNTIFS('Source Registry'!$U$2:$U$400,$A10,'Source Registry'!$V$2:$V$400,"Context (synthesized)") -> 0 | F10: Location and livestock enterprises | G10: Risk & Protection
A11: Credit and finance | B11: Lender behavior, rates, credit conditions, farm income outlook | C11: =COUNTIF('Source Registry'!$U$2:$U$400,$A11) -> 6 | D11: =COUNTIFS('Source Registry'!$U$2:$U$400,$A11,'Source Registry'!$V$2:$V$400,"Detection feed") -> 0 | E11: =COUNTIFS('Source Registry'!$U$2:$U$400,$A11,'Source Registry'!$V$2:$V$400,"Context")+COUNTIFS('Source Registry'!$U$2:$U$400,$A11,'Source Registry'!$V$2:$V$400,"Context (synthesized)") -> 1 | F11: Debt and financial health | G11: Financial Analysis; Risk & Protection
A12: Technology and structure | B12: Product approvals, new entrants, competitor or buyer moves, antitrust action | C12: =COUNTIF('Source Registry'!$U$2:$U$400,$A12) -> 9 | D12: =COUNTIFS('Source Registry'!$U$2:$U$400,$A12,'Source Registry'!$V$2:$V$400,"Detection feed") -> 0 | E12: =COUNTIFS('Source Registry'!$U$2:$U$400,$A12,'Source Registry'!$V$2:$V$400,"Context")+COUNTIFS('Source Registry'!$U$2:$U$400,$A12,'Source Registry'!$V$2:$V$400,"Context (synthesized)") -> 2 | F12: Goals, adoption plans, and competitive advantage | G12: Adoption & Efficiency; Competitive Advantage
A13: Land and ownership | B13: Land value or rent shift, program funding, foreign ownership rules, succession resources | C13: =COUNTIF('Source Registry'!$U$2:$U$400,$A13) -> 6 | D13: =COUNTIFS('Source Registry'!$U$2:$U$400,$A13,'Source Registry'!$V$2:$V$400,"Detection feed") -> 0 | E13: =COUNTIFS('Source Registry'!$U$2:$U$400,$A13,'Source Registry'!$V$2:$V$400,"Context")+COUNTIFS('Source Registry'!$U$2:$U$400,$A13,'Source Registry'!$V$2:$V$400,"Context (synthesized)") -> 2 | F13: Land tenure and legacy intent | G13: Succession; Financial Analysis
A14: Diversification-path viability | B14: A program opens or closes, a bill passes, an energy developer moves into a county, a payment changes | C14: =COUNTIF('Source Registry'!$U$2:$U$400,$A14) -> 1 | D14: =COUNTIFS('Source Registry'!$U$2:$U$400,$A14,'Source Registry'!$V$2:$V$400,"Detection feed") -> 0 | E14: =COUNTIFS('Source Registry'!$U$2:$U$400,$A14,'Source Registry'!$V$2:$V$400,"Context")+COUNTIFS('Source Registry'!$U$2:$U$400,$A14,'Source Registry'!$V$2:$V$400,"Context (synthesized)") -> 1 | F14: Shortlisted diversification paths | G14: Income Diversification
A15: MFP events | B15: New assessment or SWOT, action plan milestone due, annual review, succession plan milestone | C15: =COUNTIF('Source Registry'!$U$2:$U$400,$A15) -> 0 | D15: =COUNTIFS('Source Registry'!$U$2:$U$400,$A15,'Source Registry'!$V$2:$V$400,"Detection feed") -> 0 | E15: =COUNTIFS('Source Registry'!$U$2:$U$400,$A15,'Source Registry'!$V$2:$V$400,"Context")+COUNTIFS('Source Registry'!$U$2:$U$400,$A15,'Source Registry'!$V$2:$V$400,"Context (synthesized)") -> 0 | F15: The farm's MFP record | G15: All dimensions
A16: Context only | B16: Balance sheets, outlooks, and analysis that explain a trigger but do not fire one | C16: =COUNTIF('Source Registry'!$U$2:$U$400,$A16) -> 58 | D16: =COUNTIFS('Source Registry'!$U$2:$U$400,$A16,'Source Registry'!$V$2:$V$400,"Detection feed") -> 0 | E16: =COUNTIFS('Source Registry'!$U$2:$U$400,$A16,'Source Registry'!$V$2:$V$400,"Context")+COUNTIFS('Source Registry'!$U$2:$U$400,$A16,'Source Registry'!$V$2:$V$400,"Context (synthesized)") -> 27 | F16: All farms (context) | G16: Strategic Vision; Market Analysis
A19: Sources by retrieval tier and system role
A20: Item | B20: Sources
A21: Retrieval tier 0 (synthesized house sources) | B21: =COUNTIF('Source Registry'!$W$2:$W$400,0) -> 10
A22: Retrieval tier 1 (curated secondary) | B22: =COUNTIF('Source Registry'!$W$2:$W$400,1) -> 47
A23: Retrieval tier 2 (primary data) | B23: =COUNTIF('Source Registry'!$W$2:$W$400,2) -> 131
A24: Role: Detection feed | B24: =COUNTIF('Source Registry'!$V$2:$V$400,"Detection feed") -> 63
A25: Role: Context | B25: =COUNTIF('Source Registry'!$V$2:$V$400,"Context") -> 47
A26: Role: Context (synthesized) | B26: =COUNTIF('Source Registry'!$V$2:$V$400,"Context (synthesized)") -> 10
A27: Role: Fetch and verify | B27: =COUNTIF('Source Registry'!$V$2:$V$400,"Fetch and verify") -> 64
A28: Role: Lens prefill | B28: =COUNTIF('Source Registry'!$V$2:$V$400,"Lens prefill") -> 4
A30: Agents look in tier order: 0, then 1, then 2. Tier 2 is used only to fetch a current value, fill a gap, or verify a number that will drive a headline.

Sheet Commodity Nodes
A1: Commodity nodes: upstream drivers, co-products and downstream demand
A2: Starting map for each commodity. Edit freely; these are planning notes from general industry knowledge, not sourced statistics.
A4: Commodity | B4: Upstream drivers | C4: Co-products and derivatives to track | D4: Downstream demand and trade | E4: Best first sources (see Registry)
A5: Milk and dairy | B5: Feed (corn, soy meal, alfalfa), energy, labor, heat stress, herd size | C5: Whey, WPC34/WPC80, WPI, lactose, butterfat, cheese, nonfat dry milk, casein | D5: Cheese and ingredient plants, sports nutrition, infant formula, exports | E5: AMS Dairy Market News; NASS Milk Production; CME dairy; GDT; GATS; USDEC
A6: Corn | B6: Nitrogen fertilizer, natural gas, weather, land rent, interest rates | C6: Ethanol, DDGS, corn oil, corn gluten feed, high-fructose corn syrup | D6: Livestock feed, ethanol plants, exports | E6: WASDE; NASS Crop Progress; EIA ethanol; Export Sales; CONAB
A7: Soybeans | B7: Phosphate and potash, weather, seed and chemical costs | C7: Soybean meal, soybean oil, hulls | D7: Feed, crushers, renewable diesel and biofuel policy, exports | E7: WASDE; NOPA; Export Sales; EPA RFS; CONAB
A8: Wheat | B8: Weather, fertilizer, energy, competitor crops | C8: Flour, bran, middlings | D8: Millers, exports, competing exporter supply | E8: WASDE; PSD; Export Sales; FAS GAIN
A9: Cattle and beef | B9: Feed cost, pasture and drought, interest rates, herd rebuilding, imports | C9: Hides, tallow, variety meats, boxed beef cuts | D9: Packers, retail and foodservice, exports | E9: NASS Cattle; AMS Livestock; CME; APHIS; LMIC / CattleFax
A10: Hogs and pork | B10: Feed cost, disease risk, regulation | C10: Variety meats, lard | D10: Packers, exports, foodservice | E10: NASS Hogs and Pigs; AMS Livestock; GATS; APHIS
A11: Poultry and eggs | B11: Feed cost, avian influenza, energy | C11: Eggs and egg products, parts and variety cuts | D11: Retail, foodservice, exports | E11: AMS Egg Markets Overview; APHIS; WASDE
A12: Specialty crops | B12: Labor and visas, water, weather, tariffs, input costs | C12: Processed, dried, juice and frozen products | D12: Retail, processors, import competition, exports | E12: AMS Specialty Crops Market News; ERS outlooks; Census trade
A13: Fertilizer and farm inputs | B13: Natural gas, phosphate and potash trade, export policy, freight | C13: Nitrogen, phosphate, potash blends | D13: Cost of production across all crops | E13: DTN; AMS fertilizer reports; World Bank Pink Sheet; GATS
